[
	{
		"fact_invoice_key" : 2017,
		"invoice_key" : 373,
		"customer_key" : 12,
		"track_key" : 1793,
		"invoice_date_key" : 20130703,
		"billing_address" : "Praça Pio X, 119",
		"billing_city" : "Rio de Janeiro",
		"billing_state" : "RJ",
		"billing_country" : "Brazil",
		"billing_postal_code" : "20040-020",
		"unit_price" : 0.99,
		"quantity" : 1,
		"invoice_total" : 3.96
	},
	{
		"fact_invoice_key" : 2018,
		"invoice_key" : 373,
		"customer_key" : 12,
		"track_key" : 1795,
		"invoice_date_key" : 20130703,
		"billing_address" : "Praça Pio X, 119",
		"billing_city" : "Rio de Janeiro",
		"billing_state" : "RJ",
		"billing_country" : "Brazil",
		"billing_postal_code" : "20040-020",
		"unit_price" : 0.99,
		"quantity" : 1,
		"invoice_total" : 3.96
	},
	{
		"fact_invoice_key" : 2019,
		"invoice_key" : 373,
		"customer_key" : 12,
		"track_key" : 1797,
		"invoice_date_key" : 20130703,
		"billing_address" : "Praça Pio X, 119",
		"billing_city" : "Rio de Janeiro",
		"billing_state" : "RJ",
		"billing_country" : "Brazil",
		"billing_postal_code" : "20040-020",
		"unit_price" : 0.99,
		"quantity" : 1,
		"invoice_total" : 3.96
	},
	{
		"fact_invoice_key" : 2020,
		"invoice_key" : 373,
		"customer_key" : 12,
		"track_key" : 1799,
		"invoice_date_key" : 20130703,
		"billing_address" : "Praça Pio X, 119",
		"billing_city" : "Rio de Janeiro",
		"billing_state" : "RJ",
		"billing_country" : "Brazil",
		"billing_postal_code" : "20040-020",
		"unit_price" : 0.99,
		"quantity" : 1,
		"invoice_total" : 3.96
	},
	{
		"fact_invoice_key" : 2021,
		"invoice_key" : 374,
		"customer_key" : 16,
		"track_key" : 1803,
		"invoice_date_key" : 20130704,
		"billing_address" : "1600 Amphitheatre Parkway",
		"billing_city" : "Mountain View",
		"billing_state" : "CA",
		"billing_country" : "USA",
		"billing_postal_code" : "94043-1351",
		"unit_price" : 0.99,
		"quantity" : 1,
		"invoice_total" : 5.94
	},
	{
		"fact_invoice_key" : 2022,
		"invoice_key" : 374,
		"customer_key" : 16,
		"track_key" : 1807,
		"invoice_date_key" : 20130704,
		"billing_address" : "1600 Amphitheatre Parkway",
		"billing_city" : "Mountain View",
		"billing_state" : "CA",
		"billing_country" : "USA",
		"billing_postal_code" : "94043-1351",
		"unit_price" : 0.99,
		"quantity" : 1,
		"invoice_total" : 5.94
	},
	{
		"fact_invoice_key" : 2023,
		"invoice_key" : 374,
		"customer_key" : 16,
		"track_key" : 1811,
		"invoice_date_key" : 20130704,
		"billing_address" : "1600 Amphitheatre Parkway",
		"billing_city" : "Mountain View",
		"billing_state" : "CA",
		"billing_country" : "USA",
		"billing_postal_code" : "94043-1351",
		"unit_price" : 0.99,
		"quantity" : 1,
		"invoice_total" : 5.94
	},
	{
		"fact_invoice_key" : 2024,
		"invoice_key" : 374,
		"customer_key" : 16,
		"track_key" : 1815,
		"invoice_date_key" : 20130704,
		"billing_address" : "1600 Amphitheatre Parkway",
		"billing_city" : "Mountain View",
		"billing_state" : "CA",
		"billing_country" : "USA",
		"billing_postal_code" : "94043-1351",
		"unit_price" : 0.99,
		"quantity" : 1,
		"invoice_total" : 5.94
	},
	{
		"fact_invoice_key" : 2025,
		"invoice_key" : 374,
		"customer_key" : 16,
		"track_key" : 1819,
		"invoice_date_key" : 20130704,
		"billing_address" : "1600 Amphitheatre Parkway",
		"billing_city" : "Mountain View",
		"billing_state" : "CA",
		"billing_country" : "USA",
		"billing_postal_code" : "94043-1351",
		"unit_price" : 0.99,
		"quantity" : 1,
		"invoice_total" : 5.94
	},
	{
		"fact_invoice_key" : 2026,
		"invoice_key" : 374,
		"customer_key" : 16,
		"track_key" : 1823,
		"invoice_date_key" : 20130704,
		"billing_address" : "1600 Amphitheatre Parkway",
		"billing_city" : "Mountain View",
		"billing_state" : "CA",
		"billing_country" : "USA",
		"billing_postal_code" : "94043-1351",
		"unit_price" : 0.99,
		"quantity" : 1,
		"invoice_total" : 5.94
	},
	{
		"fact_invoice_key" : 2027,
		"invoice_key" : 375,
		"customer_key" : 22,
		"track_key" : 1829,
		"invoice_date_key" : 20130707,
		"billing_address" : "120 S Orange Ave",
		"billing_city" : "Orlando",
		"billing_state" : "FL",
		"billing_country" : "USA",
		"billing_postal_code" : "32801",
		"unit_price" : 0.99,
		"quantity" : 1,
		"invoice_total" : 8.91
	},
	{
		"fact_invoice_key" : 2028,
		"invoice_key" : 375,
		"customer_key" : 22,
		"track_key" : 1835,
		"invoice_date_key" : 20130707,
		"billing_address" : "120 S Orange Ave",
		"billing_city" : "Orlando",
		"billing_state" : "FL",
		"billing_country" : "USA",
		"billing_postal_code" : "32801",
		"unit_price" : 0.99,
		"quantity" : 1,
		"invoice_total" : 8.91
	},
	{
		"fact_invoice_key" : 2029,
		"invoice_key" : 375,
		"customer_key" : 22,
		"track_key" : 1841,
		"invoice_date_key" : 20130707,
		"billing_address" : "120 S Orange Ave",
		"billing_city" : "Orlando",
		"billing_state" : "FL",
		"billing_country" : "USA",
		"billing_postal_code" : "32801",
		"unit_price" : 0.99,
		"quantity" : 1,
		"invoice_total" : 8.91
	},
	{
		"fact_invoice_key" : 2030,
		"invoice_key" : 375,
		"customer_key" : 22,
		"track_key" : 1847,
		"invoice_date_key" : 20130707,
		"billing_address" : "120 S Orange Ave",
		"billing_city" : "Orlando",
		"billing_state" : "FL",
		"billing_country" : "USA",
		"billing_postal_code" : "32801",
		"unit_price" : 0.99,
		"quantity" : 1,
		"invoice_total" : 8.91
	},
	{
		"fact_invoice_key" : 2031,
		"invoice_key" : 375,
		"customer_key" : 22,
		"track_key" : 1853,
		"invoice_date_key" : 20130707,
		"billing_address" : "120 S Orange Ave",
		"billing_city" : "Orlando",
		"billing_state" : "FL",
		"billing_country" : "USA",
		"billing_postal_code" : "32801",
		"unit_price" : 0.99,
		"quantity" : 1,
		"invoice_total" : 8.91
	},
	{
		"fact_invoice_key" : 2032,
		"invoice_key" : 375,
		"customer_key" : 22,
		"track_key" : 1859,
		"invoice_date_key" : 20130707,
		"billing_address" : "120 S Orange Ave",
		"billing_city" : "Orlando",
		"billing_state" : "FL",
		"billing_country" : "USA",
		"billing_postal_code" : "32801",
		"unit_price" : 0.99,
		"quantity" : 1,
		"invoice_total" : 8.91
	},
	{
		"fact_invoice_key" : 2033,
		"invoice_key" : 375,
		"customer_key" : 22,
		"track_key" : 1865,
		"invoice_date_key" : 20130707,
		"billing_address" : "120 S Orange Ave",
		"billing_city" : "Orlando",
		"billing_state" : "FL",
		"billing_country" : "USA",
		"billing_postal_code" : "32801",
		"unit_price" : 0.99,
		"quantity" : 1,
		"invoice_total" : 8.91
	},
	{
		"fact_invoice_key" : 2034,
		"invoice_key" : 375,
		"customer_key" : 22,
		"track_key" : 1871,
		"invoice_date_key" : 20130707,
		"billing_address" : "120 S Orange Ave",
		"billing_city" : "Orlando",
		"billing_state" : "FL",
		"billing_country" : "USA",
		"billing_postal_code" : "32801",
		"unit_price" : 0.99,
		"quantity" : 1,
		"invoice_total" : 8.91
	},
	{
		"fact_invoice_key" : 2035,
		"invoice_key" : 375,
		"customer_key" : 22,
		"track_key" : 1877,
		"invoice_date_key" : 20130707,
		"billing_address" : "120 S Orange Ave",
		"billing_city" : "Orlando",
		"billing_state" : "FL",
		"billing_country" : "USA",
		"billing_postal_code" : "32801",
		"unit_price" : 0.99,
		"quantity" : 1,
		"invoice_total" : 8.91
	},
	{
		"fact_invoice_key" : 2036,
		"invoice_key" : 376,
		"customer_key" : 31,
		"track_key" : 1886,
		"invoice_date_key" : 20130712,
		"billing_address" : "194A Chain Lake Drive",
		"billing_city" : "Halifax",
		"billing_state" : "NS",
		"billing_country" : "Canada",
		"billing_postal_code" : "B3S 1C5",
		"unit_price" : 0.99,
		"quantity" : 1,
		"invoice_total" : 13.86
	},
	{
		"fact_invoice_key" : 2037,
		"invoice_key" : 376,
		"customer_key" : 31,
		"track_key" : 1895,
		"invoice_date_key" : 20130712,
		"billing_address" : "194A Chain Lake Drive",
		"billing_city" : "Halifax",
		"billing_state" : "NS",
		"billing_country" : "Canada",
		"billing_postal_code" : "B3S 1C5",
		"unit_price" : 0.99,
		"quantity" : 1,
		"invoice_total" : 13.86
	},
	{
		"fact_invoice_key" : 2038,
		"invoice_key" : 376,
		"customer_key" : 31,
		"track_key" : 1904,
		"invoice_date_key" : 20130712,
		"billing_address" : "194A Chain Lake Drive",
		"billing_city" : "Halifax",
		"billing_state" : "NS",
		"billing_country" : "Canada",
		"billing_postal_code" : "B3S 1C5",
		"unit_price" : 0.99,
		"quantity" : 1,
		"invoice_total" : 13.86
	},
	{
		"fact_invoice_key" : 2039,
		"invoice_key" : 376,
		"customer_key" : 31,
		"track_key" : 1913,
		"invoice_date_key" : 20130712,
		"billing_address" : "194A Chain Lake Drive",
		"billing_city" : "Halifax",
		"billing_state" : "NS",
		"billing_country" : "Canada",
		"billing_postal_code" : "B3S 1C5",
		"unit_price" : 0.99,
		"quantity" : 1,
		"invoice_total" : 13.86
	},
	{
		"fact_invoice_key" : 2040,
		"invoice_key" : 376,
		"customer_key" : 31,
		"track_key" : 1922,
		"invoice_date_key" : 20130712,
		"billing_address" : "194A Chain Lake Drive",
		"billing_city" : "Halifax",
		"billing_state" : "NS",
		"billing_country" : "Canada",
		"billing_postal_code" : "B3S 1C5",
		"unit_price" : 0.99,
		"quantity" : 1,
		"invoice_total" : 13.86
	},
	{
		"fact_invoice_key" : 2041,
		"invoice_key" : 376,
		"customer_key" : 31,
		"track_key" : 1931,
		"invoice_date_key" : 20130712,
		"billing_address" : "194A Chain Lake Drive",
		"billing_city" : "Halifax",
		"billing_state" : "NS",
		"billing_country" : "Canada",
		"billing_postal_code" : "B3S 1C5",
		"unit_price" : 0.99,
		"quantity" : 1,
		"invoice_total" : 13.86
	},
	{
		"fact_invoice_key" : 2042,
		"invoice_key" : 376,
		"customer_key" : 31,
		"track_key" : 1940,
		"invoice_date_key" : 20130712,
		"billing_address" : "194A Chain Lake Drive",
		"billing_city" : "Halifax",
		"billing_state" : "NS",
		"billing_country" : "Canada",
		"billing_postal_code" : "B3S 1C5",
		"unit_price" : 0.99,
		"quantity" : 1,
		"invoice_total" : 13.86
	},
	{
		"fact_invoice_key" : 2043,
		"invoice_key" : 376,
		"customer_key" : 31,
		"track_key" : 1949,
		"invoice_date_key" : 20130712,
		"billing_address" : "194A Chain Lake Drive",
		"billing_city" : "Halifax",
		"billing_state" : "NS",
		"billing_country" : "Canada",
		"billing_postal_code" : "B3S 1C5",
		"unit_price" : 0.99,
		"quantity" : 1,
		"invoice_total" : 13.86
	},
	{
		"fact_invoice_key" : 2044,
		"invoice_key" : 376,
		"customer_key" : 31,
		"track_key" : 1958,
		"invoice_date_key" : 20130712,
		"billing_address" : "194A Chain Lake Drive",
		"billing_city" : "Halifax",
		"billing_state" : "NS",
		"billing_country" : "Canada",
		"billing_postal_code" : "B3S 1C5",
		"unit_price" : 0.99,
		"quantity" : 1,
		"invoice_total" : 13.86
	},
	{
		"fact_invoice_key" : 2045,
		"invoice_key" : 376,
		"customer_key" : 31,
		"track_key" : 1967,
		"invoice_date_key" : 20130712,
		"billing_address" : "194A Chain Lake Drive",
		"billing_city" : "Halifax",
		"billing_state" : "NS",
		"billing_country" : "Canada",
		"billing_postal_code" : "B3S 1C5",
		"unit_price" : 0.99,
		"quantity" : 1,
		"invoice_total" : 13.86
	},
	{
		"fact_invoice_key" : 2046,
		"invoice_key" : 376,
		"customer_key" : 31,
		"track_key" : 1976,
		"invoice_date_key" : 20130712,
		"billing_address" : "194A Chain Lake Drive",
		"billing_city" : "Halifax",
		"billing_state" : "NS",
		"billing_country" : "Canada",
		"billing_postal_code" : "B3S 1C5",
		"unit_price" : 0.99,
		"quantity" : 1,
		"invoice_total" : 13.86
	},
	{
		"fact_invoice_key" : 2047,
		"invoice_key" : 376,
		"customer_key" : 31,
		"track_key" : 1985,
		"invoice_date_key" : 20130712,
		"billing_address" : "194A Chain Lake Drive",
		"billing_city" : "Halifax",
		"billing_state" : "NS",
		"billing_country" : "Canada",
		"billing_postal_code" : "B3S 1C5",
		"unit_price" : 0.99,
		"quantity" : 1,
		"invoice_total" : 13.86
	},
	{
		"fact_invoice_key" : 2048,
		"invoice_key" : 376,
		"customer_key" : 31,
		"track_key" : 1994,
		"invoice_date_key" : 20130712,
		"billing_address" : "194A Chain Lake Drive",
		"billing_city" : "Halifax",
		"billing_state" : "NS",
		"billing_country" : "Canada",
		"billing_postal_code" : "B3S 1C5",
		"unit_price" : 0.99,
		"quantity" : 1,
		"invoice_total" : 13.86
	},
	{
		"fact_invoice_key" : 2049,
		"invoice_key" : 376,
		"customer_key" : 31,
		"track_key" : 2003,
		"invoice_date_key" : 20130712,
		"billing_address" : "194A Chain Lake Drive",
		"billing_city" : "Halifax",
		"billing_state" : "NS",
		"billing_country" : "Canada",
		"billing_postal_code" : "B3S 1C5",
		"unit_price" : 0.99,
		"quantity" : 1,
		"invoice_total" : 13.86
	},
	{
		"fact_invoice_key" : 2050,
		"invoice_key" : 377,
		"customer_key" : 45,
		"track_key" : 2017,
		"invoice_date_key" : 20130720,
		"billing_address" : "Erzsébet krt. 58.",
		"billing_city" : "Budapest",
		"billing_state" : null,
		"billing_country" : "Hungary",
		"billing_postal_code" : "H-1073",
		"unit_price" : 0.99,
		"quantity" : 1,
		"invoice_total" : 0.99
	},
	{
		"fact_invoice_key" : 2051,
		"invoice_key" : 378,
		"customer_key" : 46,
		"track_key" : 2018,
		"invoice_date_key" : 20130802,
		"billing_address" : "3 Chatham Street",
		"billing_city" : "Dublin",
		"billing_state" : "Dublin",
		"billing_country" : "Ireland",
		"billing_postal_code" : null,
		"unit_price" : 0.99,
		"quantity" : 1,
		"invoice_total" : 1.98
	},
	{
		"fact_invoice_key" : 2052,
		"invoice_key" : 378,
		"customer_key" : 46,
		"track_key" : 2019,
		"invoice_date_key" : 20130802,
		"billing_address" : "3 Chatham Street",
		"billing_city" : "Dublin",
		"billing_state" : "Dublin",
		"billing_country" : "Ireland",
		"billing_postal_code" : null,
		"unit_price" : 0.99,
		"quantity" : 1,
		"invoice_total" : 1.98
	},
	{
		"fact_invoice_key" : 2053,
		"invoice_key" : 379,
		"customer_key" : 48,
		"track_key" : 2021,
		"invoice_date_key" : 20130802,
		"billing_address" : "Lijnbaansgracht 120bg",
		"billing_city" : "Amsterdam",
		"billing_state" : "VV",
		"billing_country" : "Netherlands",
		"billing_postal_code" : "1016",
		"unit_price" : 0.99,
		"quantity" : 1,
		"invoice_total" : 1.98
	},
	{
		"fact_invoice_key" : 2054,
		"invoice_key" : 379,
		"customer_key" : 48,
		"track_key" : 2023,
		"invoice_date_key" : 20130802,
		"billing_address" : "Lijnbaansgracht 120bg",
		"billing_city" : "Amsterdam",
		"billing_state" : "VV",
		"billing_country" : "Netherlands",
		"billing_postal_code" : "1016",
		"unit_price" : 0.99,
		"quantity" : 1,
		"invoice_total" : 1.98
	},
	{
		"fact_invoice_key" : 2055,
		"invoice_key" : 380,
		"customer_key" : 50,
		"track_key" : 2025,
		"invoice_date_key" : 20130803,
		"billing_address" : "C/ San Bernardo 85",
		"billing_city" : "Madrid",
		"billing_state" : null,
		"billing_country" : "Spain",
		"billing_postal_code" : "28015",
		"unit_price" : 0.99,
		"quantity" : 1,
		"invoice_total" : 3.96
	},
	{
		"fact_invoice_key" : 2056,
		"invoice_key" : 380,
		"customer_key" : 50,
		"track_key" : 2027,
		"invoice_date_key" : 20130803,
		"billing_address" : "C/ San Bernardo 85",
		"billing_city" : "Madrid",
		"billing_state" : null,
		"billing_country" : "Spain",
		"billing_postal_code" : "28015",
		"unit_price" : 0.99,
		"quantity" : 1,
		"invoice_total" : 3.96
	},
	{
		"fact_invoice_key" : 2057,
		"invoice_key" : 380,
		"customer_key" : 50,
		"track_key" : 2029,
		"invoice_date_key" : 20130803,
		"billing_address" : "C/ San Bernardo 85",
		"billing_city" : "Madrid",
		"billing_state" : null,
		"billing_country" : "Spain",
		"billing_postal_code" : "28015",
		"unit_price" : 0.99,
		"quantity" : 1,
		"invoice_total" : 3.96
	},
	{
		"fact_invoice_key" : 2058,
		"invoice_key" : 380,
		"customer_key" : 50,
		"track_key" : 2031,
		"invoice_date_key" : 20130803,
		"billing_address" : "C/ San Bernardo 85",
		"billing_city" : "Madrid",
		"billing_state" : null,
		"billing_country" : "Spain",
		"billing_postal_code" : "28015",
		"unit_price" : 0.99,
		"quantity" : 1,
		"invoice_total" : 3.96
	},
	{
		"fact_invoice_key" : 2059,
		"invoice_key" : 381,
		"customer_key" : 54,
		"track_key" : 2035,
		"invoice_date_key" : 20130804,
		"billing_address" : "110 Raeburn Pl",
		"billing_city" : "Edinburgh ",
		"billing_state" : null,
		"billing_country" : "United Kingdom",
		"billing_postal_code" : "EH4 1HH",
		"unit_price" : 0.99,
		"quantity" : 1,
		"invoice_total" : 5.94
	},
	{
		"fact_invoice_key" : 2060,
		"invoice_key" : 381,
		"customer_key" : 54,
		"track_key" : 2039,
		"invoice_date_key" : 20130804,
		"billing_address" : "110 Raeburn Pl",
		"billing_city" : "Edinburgh ",
		"billing_state" : null,
		"billing_country" : "United Kingdom",
		"billing_postal_code" : "EH4 1HH",
		"unit_price" : 0.99,
		"quantity" : 1,
		"invoice_total" : 5.94
	},
	{
		"fact_invoice_key" : 2061,
		"invoice_key" : 381,
		"customer_key" : 54,
		"track_key" : 2043,
		"invoice_date_key" : 20130804,
		"billing_address" : "110 Raeburn Pl",
		"billing_city" : "Edinburgh ",
		"billing_state" : null,
		"billing_country" : "United Kingdom",
		"billing_postal_code" : "EH4 1HH",
		"unit_price" : 0.99,
		"quantity" : 1,
		"invoice_total" : 5.94
	},
	{
		"fact_invoice_key" : 2062,
		"invoice_key" : 381,
		"customer_key" : 54,
		"track_key" : 2047,
		"invoice_date_key" : 20130804,
		"billing_address" : "110 Raeburn Pl",
		"billing_city" : "Edinburgh ",
		"billing_state" : null,
		"billing_country" : "United Kingdom",
		"billing_postal_code" : "EH4 1HH",
		"unit_price" : 0.99,
		"quantity" : 1,
		"invoice_total" : 5.94
	},
	{
		"fact_invoice_key" : 2063,
		"invoice_key" : 381,
		"customer_key" : 54,
		"track_key" : 2051,
		"invoice_date_key" : 20130804,
		"billing_address" : "110 Raeburn Pl",
		"billing_city" : "Edinburgh ",
		"billing_state" : null,
		"billing_country" : "United Kingdom",
		"billing_postal_code" : "EH4 1HH",
		"unit_price" : 0.99,
		"quantity" : 1,
		"invoice_total" : 5.94
	},
	{
		"fact_invoice_key" : 2064,
		"invoice_key" : 381,
		"customer_key" : 54,
		"track_key" : 2055,
		"invoice_date_key" : 20130804,
		"billing_address" : "110 Raeburn Pl",
		"billing_city" : "Edinburgh ",
		"billing_state" : null,
		"billing_country" : "United Kingdom",
		"billing_postal_code" : "EH4 1HH",
		"unit_price" : 0.99,
		"quantity" : 1,
		"invoice_total" : 5.94
	},
	{
		"fact_invoice_key" : 2065,
		"invoice_key" : 382,
		"customer_key" : 1,
		"track_key" : 2061,
		"invoice_date_key" : 20130807,
		"billing_address" : "Av. Brigadeiro Faria Lima, 2170",
		"billing_city" : "São José dos Campos",
		"billing_state" : "SP",
		"billing_country" : "Brazil",
		"billing_postal_code" : "12227-000",
		"unit_price" : 0.99,
		"quantity" : 1,
		"invoice_total" : 8.91
	},
	{
		"fact_invoice_key" : 2066,
		"invoice_key" : 382,
		"customer_key" : 1,
		"track_key" : 2067,
		"invoice_date_key" : 20130807,
		"billing_address" : "Av. Brigadeiro Faria Lima, 2170",
		"billing_city" : "São José dos Campos",
		"billing_state" : "SP",
		"billing_country" : "Brazil",
		"billing_postal_code" : "12227-000",
		"unit_price" : 0.99,
		"quantity" : 1,
		"invoice_total" : 8.91
	},
	{
		"fact_invoice_key" : 2067,
		"invoice_key" : 382,
		"customer_key" : 1,
		"track_key" : 2073,
		"invoice_date_key" : 20130807,
		"billing_address" : "Av. Brigadeiro Faria Lima, 2170",
		"billing_city" : "São José dos Campos",
		"billing_state" : "SP",
		"billing_country" : "Brazil",
		"billing_postal_code" : "12227-000",
		"unit_price" : 0.99,
		"quantity" : 1,
		"invoice_total" : 8.91
	},
	{
		"fact_invoice_key" : 2068,
		"invoice_key" : 382,
		"customer_key" : 1,
		"track_key" : 2079,
		"invoice_date_key" : 20130807,
		"billing_address" : "Av. Brigadeiro Faria Lima, 2170",
		"billing_city" : "São José dos Campos",
		"billing_state" : "SP",
		"billing_country" : "Brazil",
		"billing_postal_code" : "12227-000",
		"unit_price" : 0.99,
		"quantity" : 1,
		"invoice_total" : 8.91
	},
	{
		"fact_invoice_key" : 2069,
		"invoice_key" : 382,
		"customer_key" : 1,
		"track_key" : 2085,
		"invoice_date_key" : 20130807,
		"billing_address" : "Av. Brigadeiro Faria Lima, 2170",
		"billing_city" : "São José dos Campos",
		"billing_state" : "SP",
		"billing_country" : "Brazil",
		"billing_postal_code" : "12227-000",
		"unit_price" : 0.99,
		"quantity" : 1,
		"invoice_total" : 8.91
	},
	{
		"fact_invoice_key" : 2070,
		"invoice_key" : 382,
		"customer_key" : 1,
		"track_key" : 2091,
		"invoice_date_key" : 20130807,
		"billing_address" : "Av. Brigadeiro Faria Lima, 2170",
		"billing_city" : "São José dos Campos",
		"billing_state" : "SP",
		"billing_country" : "Brazil",
		"billing_postal_code" : "12227-000",
		"unit_price" : 0.99,
		"quantity" : 1,
		"invoice_total" : 8.91
	},
	{
		"fact_invoice_key" : 2071,
		"invoice_key" : 382,
		"customer_key" : 1,
		"track_key" : 2097,
		"invoice_date_key" : 20130807,
		"billing_address" : "Av. Brigadeiro Faria Lima, 2170",
		"billing_city" : "São José dos Campos",
		"billing_state" : "SP",
		"billing_country" : "Brazil",
		"billing_postal_code" : "12227-000",
		"unit_price" : 0.99,
		"quantity" : 1,
		"invoice_total" : 8.91
	},
	{
		"fact_invoice_key" : 2072,
		"invoice_key" : 382,
		"customer_key" : 1,
		"track_key" : 2103,
		"invoice_date_key" : 20130807,
		"billing_address" : "Av. Brigadeiro Faria Lima, 2170",
		"billing_city" : "São José dos Campos",
		"billing_state" : "SP",
		"billing_country" : "Brazil",
		"billing_postal_code" : "12227-000",
		"unit_price" : 0.99,
		"quantity" : 1,
		"invoice_total" : 8.91
	},
	{
		"fact_invoice_key" : 2073,
		"invoice_key" : 382,
		"customer_key" : 1,
		"track_key" : 2109,
		"invoice_date_key" : 20130807,
		"billing_address" : "Av. Brigadeiro Faria Lima, 2170",
		"billing_city" : "São José dos Campos",
		"billing_state" : "SP",
		"billing_country" : "Brazil",
		"billing_postal_code" : "12227-000",
		"unit_price" : 0.99,
		"quantity" : 1,
		"invoice_total" : 8.91
	},
	{
		"fact_invoice_key" : 2074,
		"invoice_key" : 383,
		"customer_key" : 10,
		"track_key" : 2118,
		"invoice_date_key" : 20130812,
		"billing_address" : "Rua Dr. Falcão Filho, 155",
		"billing_city" : "São Paulo",
		"billing_state" : "SP",
		"billing_country" : "Brazil",
		"billing_postal_code" : "01007-010",
		"unit_price" : 0.99,
		"quantity" : 1,
		"invoice_total" : 13.86
	},
	{
		"fact_invoice_key" : 2075,
		"invoice_key" : 383,
		"customer_key" : 10,
		"track_key" : 2127,
		"invoice_date_key" : 20130812,
		"billing_address" : "Rua Dr. Falcão Filho, 155",
		"billing_city" : "São Paulo",
		"billing_state" : "SP",
		"billing_country" : "Brazil",
		"billing_postal_code" : "01007-010",
		"unit_price" : 0.99,
		"quantity" : 1,
		"invoice_total" : 13.86
	},
	{
		"fact_invoice_key" : 2076,
		"invoice_key" : 383,
		"customer_key" : 10,
		"track_key" : 2136,
		"invoice_date_key" : 20130812,
		"billing_address" : "Rua Dr. Falcão Filho, 155",
		"billing_city" : "São Paulo",
		"billing_state" : "SP",
		"billing_country" : "Brazil",
		"billing_postal_code" : "01007-010",
		"unit_price" : 0.99,
		"quantity" : 1,
		"invoice_total" : 13.86
	},
	{
		"fact_invoice_key" : 2077,
		"invoice_key" : 383,
		"customer_key" : 10,
		"track_key" : 2145,
		"invoice_date_key" : 20130812,
		"billing_address" : "Rua Dr. Falcão Filho, 155",
		"billing_city" : "São Paulo",
		"billing_state" : "SP",
		"billing_country" : "Brazil",
		"billing_postal_code" : "01007-010",
		"unit_price" : 0.99,
		"quantity" : 1,
		"invoice_total" : 13.86
	},
	{
		"fact_invoice_key" : 2078,
		"invoice_key" : 383,
		"customer_key" : 10,
		"track_key" : 2154,
		"invoice_date_key" : 20130812,
		"billing_address" : "Rua Dr. Falcão Filho, 155",
		"billing_city" : "São Paulo",
		"billing_state" : "SP",
		"billing_country" : "Brazil",
		"billing_postal_code" : "01007-010",
		"unit_price" : 0.99,
		"quantity" : 1,
		"invoice_total" : 13.86
	},
	{
		"fact_invoice_key" : 2079,
		"invoice_key" : 383,
		"customer_key" : 10,
		"track_key" : 2163,
		"invoice_date_key" : 20130812,
		"billing_address" : "Rua Dr. Falcão Filho, 155",
		"billing_city" : "São Paulo",
		"billing_state" : "SP",
		"billing_country" : "Brazil",
		"billing_postal_code" : "01007-010",
		"unit_price" : 0.99,
		"quantity" : 1,
		"invoice_total" : 13.86
	},
	{
		"fact_invoice_key" : 2080,
		"invoice_key" : 383,
		"customer_key" : 10,
		"track_key" : 2172,
		"invoice_date_key" : 20130812,
		"billing_address" : "Rua Dr. Falcão Filho, 155",
		"billing_city" : "São Paulo",
		"billing_state" : "SP",
		"billing_country" : "Brazil",
		"billing_postal_code" : "01007-010",
		"unit_price" : 0.99,
		"quantity" : 1,
		"invoice_total" : 13.86
	},
	{
		"fact_invoice_key" : 2081,
		"invoice_key" : 383,
		"customer_key" : 10,
		"track_key" : 2181,
		"invoice_date_key" : 20130812,
		"billing_address" : "Rua Dr. Falcão Filho, 155",
		"billing_city" : "São Paulo",
		"billing_state" : "SP",
		"billing_country" : "Brazil",
		"billing_postal_code" : "01007-010",
		"unit_price" : 0.99,
		"quantity" : 1,
		"invoice_total" : 13.86
	},
	{
		"fact_invoice_key" : 2082,
		"invoice_key" : 383,
		"customer_key" : 10,
		"track_key" : 2190,
		"invoice_date_key" : 20130812,
		"billing_address" : "Rua Dr. Falcão Filho, 155",
		"billing_city" : "São Paulo",
		"billing_state" : "SP",
		"billing_country" : "Brazil",
		"billing_postal_code" : "01007-010",
		"unit_price" : 0.99,
		"quantity" : 1,
		"invoice_total" : 13.86
	},
	{
		"fact_invoice_key" : 2083,
		"invoice_key" : 383,
		"customer_key" : 10,
		"track_key" : 2199,
		"invoice_date_key" : 20130812,
		"billing_address" : "Rua Dr. Falcão Filho, 155",
		"billing_city" : "São Paulo",
		"billing_state" : "SP",
		"billing_country" : "Brazil",
		"billing_postal_code" : "01007-010",
		"unit_price" : 0.99,
		"quantity" : 1,
		"invoice_total" : 13.86
	},
	{
		"fact_invoice_key" : 2084,
		"invoice_key" : 383,
		"customer_key" : 10,
		"track_key" : 2208,
		"invoice_date_key" : 20130812,
		"billing_address" : "Rua Dr. Falcão Filho, 155",
		"billing_city" : "São Paulo",
		"billing_state" : "SP",
		"billing_country" : "Brazil",
		"billing_postal_code" : "01007-010",
		"unit_price" : 0.99,
		"quantity" : 1,
		"invoice_total" : 13.86
	},
	{
		"fact_invoice_key" : 2085,
		"invoice_key" : 383,
		"customer_key" : 10,
		"track_key" : 2217,
		"invoice_date_key" : 20130812,
		"billing_address" : "Rua Dr. Falcão Filho, 155",
		"billing_city" : "São Paulo",
		"billing_state" : "SP",
		"billing_country" : "Brazil",
		"billing_postal_code" : "01007-010",
		"unit_price" : 0.99,
		"quantity" : 1,
		"invoice_total" : 13.86
	},
	{
		"fact_invoice_key" : 2086,
		"invoice_key" : 383,
		"customer_key" : 10,
		"track_key" : 2226,
		"invoice_date_key" : 20130812,
		"billing_address" : "Rua Dr. Falcão Filho, 155",
		"billing_city" : "São Paulo",
		"billing_state" : "SP",
		"billing_country" : "Brazil",
		"billing_postal_code" : "01007-010",
		"unit_price" : 0.99,
		"quantity" : 1,
		"invoice_total" : 13.86
	},
	{
		"fact_invoice_key" : 2087,
		"invoice_key" : 383,
		"customer_key" : 10,
		"track_key" : 2235,
		"invoice_date_key" : 20130812,
		"billing_address" : "Rua Dr. Falcão Filho, 155",
		"billing_city" : "São Paulo",
		"billing_state" : "SP",
		"billing_country" : "Brazil",
		"billing_postal_code" : "01007-010",
		"unit_price" : 0.99,
		"quantity" : 1,
		"invoice_total" : 13.86
	},
	{
		"fact_invoice_key" : 2088,
		"invoice_key" : 384,
		"customer_key" : 24,
		"track_key" : 2249,
		"invoice_date_key" : 20130820,
		"billing_address" : "162 E Superior Street",
		"billing_city" : "Chicago",
		"billing_state" : "IL",
		"billing_country" : "USA",
		"billing_postal_code" : "60611",
		"unit_price" : 0.99,
		"quantity" : 1,
		"invoice_total" : 0.99
	},
	{
		"fact_invoice_key" : 2089,
		"invoice_key" : 385,
		"customer_key" : 25,
		"track_key" : 2250,
		"invoice_date_key" : 20130902,
		"billing_address" : "319 N. Frances Street",
		"billing_city" : "Madison",
		"billing_state" : "WI",
		"billing_country" : "USA",
		"billing_postal_code" : "53703",
		"unit_price" : 0.99,
		"quantity" : 1,
		"invoice_total" : 1.98
	},
	{
		"fact_invoice_key" : 2090,
		"invoice_key" : 385,
		"customer_key" : 25,
		"track_key" : 2251,
		"invoice_date_key" : 20130902,
		"billing_address" : "319 N. Frances Street",
		"billing_city" : "Madison",
		"billing_state" : "WI",
		"billing_country" : "USA",
		"billing_postal_code" : "53703",
		"unit_price" : 0.99,
		"quantity" : 1,
		"invoice_total" : 1.98
	},
	{
		"fact_invoice_key" : 2091,
		"invoice_key" : 386,
		"customer_key" : 27,
		"track_key" : 2253,
		"invoice_date_key" : 20130902,
		"billing_address" : "1033 N Park Ave",
		"billing_city" : "Tucson",
		"billing_state" : "AZ",
		"billing_country" : "USA",
		"billing_postal_code" : "85719",
		"unit_price" : 0.99,
		"quantity" : 1,
		"invoice_total" : 1.98
	},
	{
		"fact_invoice_key" : 2092,
		"invoice_key" : 386,
		"customer_key" : 27,
		"track_key" : 2255,
		"invoice_date_key" : 20130902,
		"billing_address" : "1033 N Park Ave",
		"billing_city" : "Tucson",
		"billing_state" : "AZ",
		"billing_country" : "USA",
		"billing_postal_code" : "85719",
		"unit_price" : 0.99,
		"quantity" : 1,
		"invoice_total" : 1.98
	},
	{
		"fact_invoice_key" : 2093,
		"invoice_key" : 387,
		"customer_key" : 29,
		"track_key" : 2257,
		"invoice_date_key" : 20130903,
		"billing_address" : "796 Dundas Street West",
		"billing_city" : "Toronto",
		"billing_state" : "ON",
		"billing_country" : "Canada",
		"billing_postal_code" : "M6J 1V1",
		"unit_price" : 0.99,
		"quantity" : 1,
		"invoice_total" : 3.96
	},
	{
		"fact_invoice_key" : 2094,
		"invoice_key" : 387,
		"customer_key" : 29,
		"track_key" : 2259,
		"invoice_date_key" : 20130903,
		"billing_address" : "796 Dundas Street West",
		"billing_city" : "Toronto",
		"billing_state" : "ON",
		"billing_country" : "Canada",
		"billing_postal_code" : "M6J 1V1",
		"unit_price" : 0.99,
		"quantity" : 1,
		"invoice_total" : 3.96
	},
	{
		"fact_invoice_key" : 2095,
		"invoice_key" : 387,
		"customer_key" : 29,
		"track_key" : 2261,
		"invoice_date_key" : 20130903,
		"billing_address" : "796 Dundas Street West",
		"billing_city" : "Toronto",
		"billing_state" : "ON",
		"billing_country" : "Canada",
		"billing_postal_code" : "M6J 1V1",
		"unit_price" : 0.99,
		"quantity" : 1,
		"invoice_total" : 3.96
	},
	{
		"fact_invoice_key" : 2096,
		"invoice_key" : 387,
		"customer_key" : 29,
		"track_key" : 2263,
		"invoice_date_key" : 20130903,
		"billing_address" : "796 Dundas Street West",
		"billing_city" : "Toronto",
		"billing_state" : "ON",
		"billing_country" : "Canada",
		"billing_postal_code" : "M6J 1V1",
		"unit_price" : 0.99,
		"quantity" : 1,
		"invoice_total" : 3.96
	},
	{
		"fact_invoice_key" : 2097,
		"invoice_key" : 388,
		"customer_key" : 33,
		"track_key" : 2267,
		"invoice_date_key" : 20130904,
		"billing_address" : "5112 48 Street",
		"billing_city" : "Yellowknife",
		"billing_state" : "NT",
		"billing_country" : "Canada",
		"billing_postal_code" : "X1A 1N6",
		"unit_price" : 0.99,
		"quantity" : 1,
		"invoice_total" : 5.94
	},
	{
		"fact_invoice_key" : 2098,
		"invoice_key" : 388,
		"customer_key" : 33,
		"track_key" : 2271,
		"invoice_date_key" : 20130904,
		"billing_address" : "5112 48 Street",
		"billing_city" : "Yellowknife",
		"billing_state" : "NT",
		"billing_country" : "Canada",
		"billing_postal_code" : "X1A 1N6",
		"unit_price" : 0.99,
		"quantity" : 1,
		"invoice_total" : 5.94
	},
	{
		"fact_invoice_key" : 2099,
		"invoice_key" : 388,
		"customer_key" : 33,
		"track_key" : 2275,
		"invoice_date_key" : 20130904,
		"billing_address" : "5112 48 Street",
		"billing_city" : "Yellowknife",
		"billing_state" : "NT",
		"billing_country" : "Canada",
		"billing_postal_code" : "X1A 1N6",
		"unit_price" : 0.99,
		"quantity" : 1,
		"invoice_total" : 5.94
	},
	{
		"fact_invoice_key" : 2100,
		"invoice_key" : 388,
		"customer_key" : 33,
		"track_key" : 2279,
		"invoice_date_key" : 20130904,
		"billing_address" : "5112 48 Street",
		"billing_city" : "Yellowknife",
		"billing_state" : "NT",
		"billing_country" : "Canada",
		"billing_postal_code" : "X1A 1N6",
		"unit_price" : 0.99,
		"quantity" : 1,
		"invoice_total" : 5.94
	},
	{
		"fact_invoice_key" : 2101,
		"invoice_key" : 388,
		"customer_key" : 33,
		"track_key" : 2283,
		"invoice_date_key" : 20130904,
		"billing_address" : "5112 48 Street",
		"billing_city" : "Yellowknife",
		"billing_state" : "NT",
		"billing_country" : "Canada",
		"billing_postal_code" : "X1A 1N6",
		"unit_price" : 0.99,
		"quantity" : 1,
		"invoice_total" : 5.94
	},
	{
		"fact_invoice_key" : 2102,
		"invoice_key" : 388,
		"customer_key" : 33,
		"track_key" : 2287,
		"invoice_date_key" : 20130904,
		"billing_address" : "5112 48 Street",
		"billing_city" : "Yellowknife",
		"billing_state" : "NT",
		"billing_country" : "Canada",
		"billing_postal_code" : "X1A 1N6",
		"unit_price" : 0.99,
		"quantity" : 1,
		"invoice_total" : 5.94
	},
	{
		"fact_invoice_key" : 2103,
		"invoice_key" : 389,
		"customer_key" : 39,
		"track_key" : 2293,
		"invoice_date_key" : 20130907,
		"billing_address" : "4, Rue Milton",
		"billing_city" : "Paris",
		"billing_state" : null,
		"billing_country" : "France",
		"billing_postal_code" : "75009",
		"unit_price" : 0.99,
		"quantity" : 1,
		"invoice_total" : 8.91
	},
	{
		"fact_invoice_key" : 2104,
		"invoice_key" : 389,
		"customer_key" : 39,
		"track_key" : 2299,
		"invoice_date_key" : 20130907,
		"billing_address" : "4, Rue Milton",
		"billing_city" : "Paris",
		"billing_state" : null,
		"billing_country" : "France",
		"billing_postal_code" : "75009",
		"unit_price" : 0.99,
		"quantity" : 1,
		"invoice_total" : 8.91
	},
	{
		"fact_invoice_key" : 2105,
		"invoice_key" : 389,
		"customer_key" : 39,
		"track_key" : 2305,
		"invoice_date_key" : 20130907,
		"billing_address" : "4, Rue Milton",
		"billing_city" : "Paris",
		"billing_state" : null,
		"billing_country" : "France",
		"billing_postal_code" : "75009",
		"unit_price" : 0.99,
		"quantity" : 1,
		"invoice_total" : 8.91
	},
	{
		"fact_invoice_key" : 2106,
		"invoice_key" : 389,
		"customer_key" : 39,
		"track_key" : 2311,
		"invoice_date_key" : 20130907,
		"billing_address" : "4, Rue Milton",
		"billing_city" : "Paris",
		"billing_state" : null,
		"billing_country" : "France",
		"billing_postal_code" : "75009",
		"unit_price" : 0.99,
		"quantity" : 1,
		"invoice_total" : 8.91
	},
	{
		"fact_invoice_key" : 2107,
		"invoice_key" : 389,
		"customer_key" : 39,
		"track_key" : 2317,
		"invoice_date_key" : 20130907,
		"billing_address" : "4, Rue Milton",
		"billing_city" : "Paris",
		"billing_state" : null,
		"billing_country" : "France",
		"billing_postal_code" : "75009",
		"unit_price" : 0.99,
		"quantity" : 1,
		"invoice_total" : 8.91
	},
	{
		"fact_invoice_key" : 2108,
		"invoice_key" : 389,
		"customer_key" : 39,
		"track_key" : 2323,
		"invoice_date_key" : 20130907,
		"billing_address" : "4, Rue Milton",
		"billing_city" : "Paris",
		"billing_state" : null,
		"billing_country" : "France",
		"billing_postal_code" : "75009",
		"unit_price" : 0.99,
		"quantity" : 1,
		"invoice_total" : 8.91
	},
	{
		"fact_invoice_key" : 2109,
		"invoice_key" : 389,
		"customer_key" : 39,
		"track_key" : 2329,
		"invoice_date_key" : 20130907,
		"billing_address" : "4, Rue Milton",
		"billing_city" : "Paris",
		"billing_state" : null,
		"billing_country" : "France",
		"billing_postal_code" : "75009",
		"unit_price" : 0.99,
		"quantity" : 1,
		"invoice_total" : 8.91
	},
	{
		"fact_invoice_key" : 2110,
		"invoice_key" : 389,
		"customer_key" : 39,
		"track_key" : 2335,
		"invoice_date_key" : 20130907,
		"billing_address" : "4, Rue Milton",
		"billing_city" : "Paris",
		"billing_state" : null,
		"billing_country" : "France",
		"billing_postal_code" : "75009",
		"unit_price" : 0.99,
		"quantity" : 1,
		"invoice_total" : 8.91
	},
	{
		"fact_invoice_key" : 2111,
		"invoice_key" : 389,
		"customer_key" : 39,
		"track_key" : 2341,
		"invoice_date_key" : 20130907,
		"billing_address" : "4, Rue Milton",
		"billing_city" : "Paris",
		"billing_state" : null,
		"billing_country" : "France",
		"billing_postal_code" : "75009",
		"unit_price" : 0.99,
		"quantity" : 1,
		"invoice_total" : 8.91
	},
	{
		"fact_invoice_key" : 2112,
		"invoice_key" : 390,
		"customer_key" : 48,
		"track_key" : 2350,
		"invoice_date_key" : 20130912,
		"billing_address" : "Lijnbaansgracht 120bg",
		"billing_city" : "Amsterdam",
		"billing_state" : "VV",
		"billing_country" : "Netherlands",
		"billing_postal_code" : "1016",
		"unit_price" : 0.99,
		"quantity" : 1,
		"invoice_total" : 13.86
	},
	{
		"fact_invoice_key" : 2113,
		"invoice_key" : 390,
		"customer_key" : 48,
		"track_key" : 2359,
		"invoice_date_key" : 20130912,
		"billing_address" : "Lijnbaansgracht 120bg",
		"billing_city" : "Amsterdam",
		"billing_state" : "VV",
		"billing_country" : "Netherlands",
		"billing_postal_code" : "1016",
		"unit_price" : 0.99,
		"quantity" : 1,
		"invoice_total" : 13.86
	},
	{
		"fact_invoice_key" : 2114,
		"invoice_key" : 390,
		"customer_key" : 48,
		"track_key" : 2368,
		"invoice_date_key" : 20130912,
		"billing_address" : "Lijnbaansgracht 120bg",
		"billing_city" : "Amsterdam",
		"billing_state" : "VV",
		"billing_country" : "Netherlands",
		"billing_postal_code" : "1016",
		"unit_price" : 0.99,
		"quantity" : 1,
		"invoice_total" : 13.86
	},
	{
		"fact_invoice_key" : 2115,
		"invoice_key" : 390,
		"customer_key" : 48,
		"track_key" : 2377,
		"invoice_date_key" : 20130912,
		"billing_address" : "Lijnbaansgracht 120bg",
		"billing_city" : "Amsterdam",
		"billing_state" : "VV",
		"billing_country" : "Netherlands",
		"billing_postal_code" : "1016",
		"unit_price" : 0.99,
		"quantity" : 1,
		"invoice_total" : 13.86
	},
	{
		"fact_invoice_key" : 2116,
		"invoice_key" : 390,
		"customer_key" : 48,
		"track_key" : 2386,
		"invoice_date_key" : 20130912,
		"billing_address" : "Lijnbaansgracht 120bg",
		"billing_city" : "Amsterdam",
		"billing_state" : "VV",
		"billing_country" : "Netherlands",
		"billing_postal_code" : "1016",
		"unit_price" : 0.99,
		"quantity" : 1,
		"invoice_total" : 13.86
	},
	{
		"fact_invoice_key" : 2117,
		"invoice_key" : 390,
		"customer_key" : 48,
		"track_key" : 2395,
		"invoice_date_key" : 20130912,
		"billing_address" : "Lijnbaansgracht 120bg",
		"billing_city" : "Amsterdam",
		"billing_state" : "VV",
		"billing_country" : "Netherlands",
		"billing_postal_code" : "1016",
		"unit_price" : 0.99,
		"quantity" : 1,
		"invoice_total" : 13.86
	},
	{
		"fact_invoice_key" : 2118,
		"invoice_key" : 390,
		"customer_key" : 48,
		"track_key" : 2404,
		"invoice_date_key" : 20130912,
		"billing_address" : "Lijnbaansgracht 120bg",
		"billing_city" : "Amsterdam",
		"billing_state" : "VV",
		"billing_country" : "Netherlands",
		"billing_postal_code" : "1016",
		"unit_price" : 0.99,
		"quantity" : 1,
		"invoice_total" : 13.86
	},
	{
		"fact_invoice_key" : 2119,
		"invoice_key" : 390,
		"customer_key" : 48,
		"track_key" : 2413,
		"invoice_date_key" : 20130912,
		"billing_address" : "Lijnbaansgracht 120bg",
		"billing_city" : "Amsterdam",
		"billing_state" : "VV",
		"billing_country" : "Netherlands",
		"billing_postal_code" : "1016",
		"unit_price" : 0.99,
		"quantity" : 1,
		"invoice_total" : 13.86
	},
	{
		"fact_invoice_key" : 2120,
		"invoice_key" : 390,
		"customer_key" : 48,
		"track_key" : 2422,
		"invoice_date_key" : 20130912,
		"billing_address" : "Lijnbaansgracht 120bg",
		"billing_city" : "Amsterdam",
		"billing_state" : "VV",
		"billing_country" : "Netherlands",
		"billing_postal_code" : "1016",
		"unit_price" : 0.99,
		"quantity" : 1,
		"invoice_total" : 13.86
	},
	{
		"fact_invoice_key" : 2121,
		"invoice_key" : 390,
		"customer_key" : 48,
		"track_key" : 2431,
		"invoice_date_key" : 20130912,
		"billing_address" : "Lijnbaansgracht 120bg",
		"billing_city" : "Amsterdam",
		"billing_state" : "VV",
		"billing_country" : "Netherlands",
		"billing_postal_code" : "1016",
		"unit_price" : 0.99,
		"quantity" : 1,
		"invoice_total" : 13.86
	},
	{
		"fact_invoice_key" : 2122,
		"invoice_key" : 390,
		"customer_key" : 48,
		"track_key" : 2440,
		"invoice_date_key" : 20130912,
		"billing_address" : "Lijnbaansgracht 120bg",
		"billing_city" : "Amsterdam",
		"billing_state" : "VV",
		"billing_country" : "Netherlands",
		"billing_postal_code" : "1016",
		"unit_price" : 0.99,
		"quantity" : 1,
		"invoice_total" : 13.86
	},
	{
		"fact_invoice_key" : 2123,
		"invoice_key" : 390,
		"customer_key" : 48,
		"track_key" : 2449,
		"invoice_date_key" : 20130912,
		"billing_address" : "Lijnbaansgracht 120bg",
		"billing_city" : "Amsterdam",
		"billing_state" : "VV",
		"billing_country" : "Netherlands",
		"billing_postal_code" : "1016",
		"unit_price" : 0.99,
		"quantity" : 1,
		"invoice_total" : 13.86
	},
	{
		"fact_invoice_key" : 2124,
		"invoice_key" : 390,
		"customer_key" : 48,
		"track_key" : 2458,
		"invoice_date_key" : 20130912,
		"billing_address" : "Lijnbaansgracht 120bg",
		"billing_city" : "Amsterdam",
		"billing_state" : "VV",
		"billing_country" : "Netherlands",
		"billing_postal_code" : "1016",
		"unit_price" : 0.99,
		"quantity" : 1,
		"invoice_total" : 13.86
	},
	{
		"fact_invoice_key" : 2125,
		"invoice_key" : 390,
		"customer_key" : 48,
		"track_key" : 2467,
		"invoice_date_key" : 20130912,
		"billing_address" : "Lijnbaansgracht 120bg",
		"billing_city" : "Amsterdam",
		"billing_state" : "VV",
		"billing_country" : "Netherlands",
		"billing_postal_code" : "1016",
		"unit_price" : 0.99,
		"quantity" : 1,
		"invoice_total" : 13.86
	},
	{
		"fact_invoice_key" : 2126,
		"invoice_key" : 391,
		"customer_key" : 3,
		"track_key" : 2481,
		"invoice_date_key" : 20130920,
		"billing_address" : "1498 rue Bélanger",
		"billing_city" : "Montréal",
		"billing_state" : "QC",
		"billing_country" : "Canada",
		"billing_postal_code" : "H2G 1A7",
		"unit_price" : 0.99,
		"quantity" : 1,
		"invoice_total" : 0.99
	},
	{
		"fact_invoice_key" : 2127,
		"invoice_key" : 392,
		"customer_key" : 4,
		"track_key" : 2482,
		"invoice_date_key" : 20131003,
		"billing_address" : "Ullevålsveien 14",
		"billing_city" : "Oslo",
		"billing_state" : null,
		"billing_country" : "Norway",
		"billing_postal_code" : "0171",
		"unit_price" : 0.99,
		"quantity" : 1,
		"invoice_total" : 1.98
	},
	{
		"fact_invoice_key" : 2128,
		"invoice_key" : 392,
		"customer_key" : 4,
		"track_key" : 2483,
		"invoice_date_key" : 20131003,
		"billing_address" : "Ullevålsveien 14",
		"billing_city" : "Oslo",
		"billing_state" : null,
		"billing_country" : "Norway",
		"billing_postal_code" : "0171",
		"unit_price" : 0.99,
		"quantity" : 1,
		"invoice_total" : 1.98
	},
	{
		"fact_invoice_key" : 2129,
		"invoice_key" : 393,
		"customer_key" : 6,
		"track_key" : 2485,
		"invoice_date_key" : 20131003,
		"billing_address" : "Rilská 3174/6",
		"billing_city" : "Prague",
		"billing_state" : null,
		"billing_country" : "Czech Republic",
		"billing_postal_code" : "14300",
		"unit_price" : 0.99,
		"quantity" : 1,
		"invoice_total" : 1.98
	},
	{
		"fact_invoice_key" : 2130,
		"invoice_key" : 393,
		"customer_key" : 6,
		"track_key" : 2487,
		"invoice_date_key" : 20131003,
		"billing_address" : "Rilská 3174/6",
		"billing_city" : "Prague",
		"billing_state" : null,
		"billing_country" : "Czech Republic",
		"billing_postal_code" : "14300",
		"unit_price" : 0.99,
		"quantity" : 1,
		"invoice_total" : 1.98
	},
	{
		"fact_invoice_key" : 2131,
		"invoice_key" : 394,
		"customer_key" : 8,
		"track_key" : 2489,
		"invoice_date_key" : 20131004,
		"billing_address" : "Grétrystraat 63",
		"billing_city" : "Brussels",
		"billing_state" : null,
		"billing_country" : "Belgium",
		"billing_postal_code" : "1000",
		"unit_price" : 0.99,
		"quantity" : 1,
		"invoice_total" : 3.96
	},
	{
		"fact_invoice_key" : 2132,
		"invoice_key" : 394,
		"customer_key" : 8,
		"track_key" : 2491,
		"invoice_date_key" : 20131004,
		"billing_address" : "Grétrystraat 63",
		"billing_city" : "Brussels",
		"billing_state" : null,
		"billing_country" : "Belgium",
		"billing_postal_code" : "1000",
		"unit_price" : 0.99,
		"quantity" : 1,
		"invoice_total" : 3.96
	},
	{
		"fact_invoice_key" : 2133,
		"invoice_key" : 394,
		"customer_key" : 8,
		"track_key" : 2493,
		"invoice_date_key" : 20131004,
		"billing_address" : "Grétrystraat 63",
		"billing_city" : "Brussels",
		"billing_state" : null,
		"billing_country" : "Belgium",
		"billing_postal_code" : "1000",
		"unit_price" : 0.99,
		"quantity" : 1,
		"invoice_total" : 3.96
	},
	{
		"fact_invoice_key" : 2134,
		"invoice_key" : 394,
		"customer_key" : 8,
		"track_key" : 2495,
		"invoice_date_key" : 20131004,
		"billing_address" : "Grétrystraat 63",
		"billing_city" : "Brussels",
		"billing_state" : null,
		"billing_country" : "Belgium",
		"billing_postal_code" : "1000",
		"unit_price" : 0.99,
		"quantity" : 1,
		"invoice_total" : 3.96
	},
	{
		"fact_invoice_key" : 2135,
		"invoice_key" : 395,
		"customer_key" : 12,
		"track_key" : 2499,
		"invoice_date_key" : 20131005,
		"billing_address" : "Praça Pio X, 119",
		"billing_city" : "Rio de Janeiro",
		"billing_state" : "RJ",
		"billing_country" : "Brazil",
		"billing_postal_code" : "20040-020",
		"unit_price" : 0.99,
		"quantity" : 1,
		"invoice_total" : 5.94
	},
	{
		"fact_invoice_key" : 2136,
		"invoice_key" : 395,
		"customer_key" : 12,
		"track_key" : 2503,
		"invoice_date_key" : 20131005,
		"billing_address" : "Praça Pio X, 119",
		"billing_city" : "Rio de Janeiro",
		"billing_state" : "RJ",
		"billing_country" : "Brazil",
		"billing_postal_code" : "20040-020",
		"unit_price" : 0.99,
		"quantity" : 1,
		"invoice_total" : 5.94
	},
	{
		"fact_invoice_key" : 2137,
		"invoice_key" : 395,
		"customer_key" : 12,
		"track_key" : 2507,
		"invoice_date_key" : 20131005,
		"billing_address" : "Praça Pio X, 119",
		"billing_city" : "Rio de Janeiro",
		"billing_state" : "RJ",
		"billing_country" : "Brazil",
		"billing_postal_code" : "20040-020",
		"unit_price" : 0.99,
		"quantity" : 1,
		"invoice_total" : 5.94
	},
	{
		"fact_invoice_key" : 2138,
		"invoice_key" : 395,
		"customer_key" : 12,
		"track_key" : 2511,
		"invoice_date_key" : 20131005,
		"billing_address" : "Praça Pio X, 119",
		"billing_city" : "Rio de Janeiro",
		"billing_state" : "RJ",
		"billing_country" : "Brazil",
		"billing_postal_code" : "20040-020",
		"unit_price" : 0.99,
		"quantity" : 1,
		"invoice_total" : 5.94
	},
	{
		"fact_invoice_key" : 2139,
		"invoice_key" : 395,
		"customer_key" : 12,
		"track_key" : 2515,
		"invoice_date_key" : 20131005,
		"billing_address" : "Praça Pio X, 119",
		"billing_city" : "Rio de Janeiro",
		"billing_state" : "RJ",
		"billing_country" : "Brazil",
		"billing_postal_code" : "20040-020",
		"unit_price" : 0.99,
		"quantity" : 1,
		"invoice_total" : 5.94
	},
	{
		"fact_invoice_key" : 2140,
		"invoice_key" : 395,
		"customer_key" : 12,
		"track_key" : 2519,
		"invoice_date_key" : 20131005,
		"billing_address" : "Praça Pio X, 119",
		"billing_city" : "Rio de Janeiro",
		"billing_state" : "RJ",
		"billing_country" : "Brazil",
		"billing_postal_code" : "20040-020",
		"unit_price" : 0.99,
		"quantity" : 1,
		"invoice_total" : 5.94
	},
	{
		"fact_invoice_key" : 2141,
		"invoice_key" : 396,
		"customer_key" : 18,
		"track_key" : 2525,
		"invoice_date_key" : 20131008,
		"billing_address" : "627 Broadway",
		"billing_city" : "New York",
		"billing_state" : "NY",
		"billing_country" : "USA",
		"billing_postal_code" : "10012-2612",
		"unit_price" : 0.99,
		"quantity" : 1,
		"invoice_total" : 8.91
	},
	{
		"fact_invoice_key" : 2142,
		"invoice_key" : 396,
		"customer_key" : 18,
		"track_key" : 2531,
		"invoice_date_key" : 20131008,
		"billing_address" : "627 Broadway",
		"billing_city" : "New York",
		"billing_state" : "NY",
		"billing_country" : "USA",
		"billing_postal_code" : "10012-2612",
		"unit_price" : 0.99,
		"quantity" : 1,
		"invoice_total" : 8.91
	},
	{
		"fact_invoice_key" : 2143,
		"invoice_key" : 396,
		"customer_key" : 18,
		"track_key" : 2537,
		"invoice_date_key" : 20131008,
		"billing_address" : "627 Broadway",
		"billing_city" : "New York",
		"billing_state" : "NY",
		"billing_country" : "USA",
		"billing_postal_code" : "10012-2612",
		"unit_price" : 0.99,
		"quantity" : 1,
		"invoice_total" : 8.91
	},
	{
		"fact_invoice_key" : 2144,
		"invoice_key" : 396,
		"customer_key" : 18,
		"track_key" : 2543,
		"invoice_date_key" : 20131008,
		"billing_address" : "627 Broadway",
		"billing_city" : "New York",
		"billing_state" : "NY",
		"billing_country" : "USA",
		"billing_postal_code" : "10012-2612",
		"unit_price" : 0.99,
		"quantity" : 1,
		"invoice_total" : 8.91
	},
	{
		"fact_invoice_key" : 2145,
		"invoice_key" : 396,
		"customer_key" : 18,
		"track_key" : 2549,
		"invoice_date_key" : 20131008,
		"billing_address" : "627 Broadway",
		"billing_city" : "New York",
		"billing_state" : "NY",
		"billing_country" : "USA",
		"billing_postal_code" : "10012-2612",
		"unit_price" : 0.99,
		"quantity" : 1,
		"invoice_total" : 8.91
	},
	{
		"fact_invoice_key" : 2146,
		"invoice_key" : 396,
		"customer_key" : 18,
		"track_key" : 2555,
		"invoice_date_key" : 20131008,
		"billing_address" : "627 Broadway",
		"billing_city" : "New York",
		"billing_state" : "NY",
		"billing_country" : "USA",
		"billing_postal_code" : "10012-2612",
		"unit_price" : 0.99,
		"quantity" : 1,
		"invoice_total" : 8.91
	},
	{
		"fact_invoice_key" : 2147,
		"invoice_key" : 396,
		"customer_key" : 18,
		"track_key" : 2561,
		"invoice_date_key" : 20131008,
		"billing_address" : "627 Broadway",
		"billing_city" : "New York",
		"billing_state" : "NY",
		"billing_country" : "USA",
		"billing_postal_code" : "10012-2612",
		"unit_price" : 0.99,
		"quantity" : 1,
		"invoice_total" : 8.91
	},
	{
		"fact_invoice_key" : 2148,
		"invoice_key" : 396,
		"customer_key" : 18,
		"track_key" : 2567,
		"invoice_date_key" : 20131008,
		"billing_address" : "627 Broadway",
		"billing_city" : "New York",
		"billing_state" : "NY",
		"billing_country" : "USA",
		"billing_postal_code" : "10012-2612",
		"unit_price" : 0.99,
		"quantity" : 1,
		"invoice_total" : 8.91
	},
	{
		"fact_invoice_key" : 2149,
		"invoice_key" : 396,
		"customer_key" : 18,
		"track_key" : 2573,
		"invoice_date_key" : 20131008,
		"billing_address" : "627 Broadway",
		"billing_city" : "New York",
		"billing_state" : "NY",
		"billing_country" : "USA",
		"billing_postal_code" : "10012-2612",
		"unit_price" : 0.99,
		"quantity" : 1,
		"invoice_total" : 8.91
	},
	{
		"fact_invoice_key" : 2150,
		"invoice_key" : 397,
		"customer_key" : 27,
		"track_key" : 2582,
		"invoice_date_key" : 20131013,
		"billing_address" : "1033 N Park Ave",
		"billing_city" : "Tucson",
		"billing_state" : "AZ",
		"billing_country" : "USA",
		"billing_postal_code" : "85719",
		"unit_price" : 0.99,
		"quantity" : 1,
		"invoice_total" : 13.86
	},
	{
		"fact_invoice_key" : 2151,
		"invoice_key" : 397,
		"customer_key" : 27,
		"track_key" : 2591,
		"invoice_date_key" : 20131013,
		"billing_address" : "1033 N Park Ave",
		"billing_city" : "Tucson",
		"billing_state" : "AZ",
		"billing_country" : "USA",
		"billing_postal_code" : "85719",
		"unit_price" : 0.99,
		"quantity" : 1,
		"invoice_total" : 13.86
	},
	{
		"fact_invoice_key" : 2152,
		"invoice_key" : 397,
		"customer_key" : 27,
		"track_key" : 2600,
		"invoice_date_key" : 20131013,
		"billing_address" : "1033 N Park Ave",
		"billing_city" : "Tucson",
		"billing_state" : "AZ",
		"billing_country" : "USA",
		"billing_postal_code" : "85719",
		"unit_price" : 0.99,
		"quantity" : 1,
		"invoice_total" : 13.86
	},
	{
		"fact_invoice_key" : 2153,
		"invoice_key" : 397,
		"customer_key" : 27,
		"track_key" : 2609,
		"invoice_date_key" : 20131013,
		"billing_address" : "1033 N Park Ave",
		"billing_city" : "Tucson",
		"billing_state" : "AZ",
		"billing_country" : "USA",
		"billing_postal_code" : "85719",
		"unit_price" : 0.99,
		"quantity" : 1,
		"invoice_total" : 13.86
	},
	{
		"fact_invoice_key" : 2154,
		"invoice_key" : 397,
		"customer_key" : 27,
		"track_key" : 2618,
		"invoice_date_key" : 20131013,
		"billing_address" : "1033 N Park Ave",
		"billing_city" : "Tucson",
		"billing_state" : "AZ",
		"billing_country" : "USA",
		"billing_postal_code" : "85719",
		"unit_price" : 0.99,
		"quantity" : 1,
		"invoice_total" : 13.86
	},
	{
		"fact_invoice_key" : 2155,
		"invoice_key" : 397,
		"customer_key" : 27,
		"track_key" : 2627,
		"invoice_date_key" : 20131013,
		"billing_address" : "1033 N Park Ave",
		"billing_city" : "Tucson",
		"billing_state" : "AZ",
		"billing_country" : "USA",
		"billing_postal_code" : "85719",
		"unit_price" : 0.99,
		"quantity" : 1,
		"invoice_total" : 13.86
	},
	{
		"fact_invoice_key" : 2156,
		"invoice_key" : 397,
		"customer_key" : 27,
		"track_key" : 2636,
		"invoice_date_key" : 20131013,
		"billing_address" : "1033 N Park Ave",
		"billing_city" : "Tucson",
		"billing_state" : "AZ",
		"billing_country" : "USA",
		"billing_postal_code" : "85719",
		"unit_price" : 0.99,
		"quantity" : 1,
		"invoice_total" : 13.86
	},
	{
		"fact_invoice_key" : 2157,
		"invoice_key" : 397,
		"customer_key" : 27,
		"track_key" : 2645,
		"invoice_date_key" : 20131013,
		"billing_address" : "1033 N Park Ave",
		"billing_city" : "Tucson",
		"billing_state" : "AZ",
		"billing_country" : "USA",
		"billing_postal_code" : "85719",
		"unit_price" : 0.99,
		"quantity" : 1,
		"invoice_total" : 13.86
	},
	{
		"fact_invoice_key" : 2158,
		"invoice_key" : 397,
		"customer_key" : 27,
		"track_key" : 2654,
		"invoice_date_key" : 20131013,
		"billing_address" : "1033 N Park Ave",
		"billing_city" : "Tucson",
		"billing_state" : "AZ",
		"billing_country" : "USA",
		"billing_postal_code" : "85719",
		"unit_price" : 0.99,
		"quantity" : 1,
		"invoice_total" : 13.86
	},
	{
		"fact_invoice_key" : 2159,
		"invoice_key" : 397,
		"customer_key" : 27,
		"track_key" : 2663,
		"invoice_date_key" : 20131013,
		"billing_address" : "1033 N Park Ave",
		"billing_city" : "Tucson",
		"billing_state" : "AZ",
		"billing_country" : "USA",
		"billing_postal_code" : "85719",
		"unit_price" : 0.99,
		"quantity" : 1,
		"invoice_total" : 13.86
	},
	{
		"fact_invoice_key" : 2160,
		"invoice_key" : 397,
		"customer_key" : 27,
		"track_key" : 2672,
		"invoice_date_key" : 20131013,
		"billing_address" : "1033 N Park Ave",
		"billing_city" : "Tucson",
		"billing_state" : "AZ",
		"billing_country" : "USA",
		"billing_postal_code" : "85719",
		"unit_price" : 0.99,
		"quantity" : 1,
		"invoice_total" : 13.86
	},
	{
		"fact_invoice_key" : 2161,
		"invoice_key" : 397,
		"customer_key" : 27,
		"track_key" : 2681,
		"invoice_date_key" : 20131013,
		"billing_address" : "1033 N Park Ave",
		"billing_city" : "Tucson",
		"billing_state" : "AZ",
		"billing_country" : "USA",
		"billing_postal_code" : "85719",
		"unit_price" : 0.99,
		"quantity" : 1,
		"invoice_total" : 13.86
	},
	{
		"fact_invoice_key" : 2162,
		"invoice_key" : 397,
		"customer_key" : 27,
		"track_key" : 2690,
		"invoice_date_key" : 20131013,
		"billing_address" : "1033 N Park Ave",
		"billing_city" : "Tucson",
		"billing_state" : "AZ",
		"billing_country" : "USA",
		"billing_postal_code" : "85719",
		"unit_price" : 0.99,
		"quantity" : 1,
		"invoice_total" : 13.86
	},
	{
		"fact_invoice_key" : 2163,
		"invoice_key" : 397,
		"customer_key" : 27,
		"track_key" : 2699,
		"invoice_date_key" : 20131013,
		"billing_address" : "1033 N Park Ave",
		"billing_city" : "Tucson",
		"billing_state" : "AZ",
		"billing_country" : "USA",
		"billing_postal_code" : "85719",
		"unit_price" : 0.99,
		"quantity" : 1,
		"invoice_total" : 13.86
	},
	{
		"fact_invoice_key" : 2164,
		"invoice_key" : 398,
		"customer_key" : 41,
		"track_key" : 2713,
		"invoice_date_key" : 20131021,
		"billing_address" : "11, Place Bellecour",
		"billing_city" : "Lyon",
		"billing_state" : null,
		"billing_country" : "France",
		"billing_postal_code" : "69002",
		"unit_price" : 0.99,
		"quantity" : 1,
		"invoice_total" : 0.99
	},
	{
		"fact_invoice_key" : 2165,
		"invoice_key" : 399,
		"customer_key" : 42,
		"track_key" : 2714,
		"invoice_date_key" : 20131103,
		"billing_address" : "9, Place Louis Barthou",
		"billing_city" : "Bordeaux",
		"billing_state" : null,
		"billing_country" : "France",
		"billing_postal_code" : "33000",
		"unit_price" : 0.99,
		"quantity" : 1,
		"invoice_total" : 1.98
	},
	{
		"fact_invoice_key" : 2166,
		"invoice_key" : 399,
		"customer_key" : 42,
		"track_key" : 2715,
		"invoice_date_key" : 20131103,
		"billing_address" : "9, Place Louis Barthou",
		"billing_city" : "Bordeaux",
		"billing_state" : null,
		"billing_country" : "France",
		"billing_postal_code" : "33000",
		"unit_price" : 0.99,
		"quantity" : 1,
		"invoice_total" : 1.98
	},
	{
		"fact_invoice_key" : 2167,
		"invoice_key" : 400,
		"customer_key" : 44,
		"track_key" : 2717,
		"invoice_date_key" : 20131103,
		"billing_address" : "Porthaninkatu 9",
		"billing_city" : "Helsinki",
		"billing_state" : null,
		"billing_country" : "Finland",
		"billing_postal_code" : "00530",
		"unit_price" : 0.99,
		"quantity" : 1,
		"invoice_total" : 1.98
	},
	{
		"fact_invoice_key" : 2168,
		"invoice_key" : 400,
		"customer_key" : 44,
		"track_key" : 2719,
		"invoice_date_key" : 20131103,
		"billing_address" : "Porthaninkatu 9",
		"billing_city" : "Helsinki",
		"billing_state" : null,
		"billing_country" : "Finland",
		"billing_postal_code" : "00530",
		"unit_price" : 0.99,
		"quantity" : 1,
		"invoice_total" : 1.98
	},
	{
		"fact_invoice_key" : 2169,
		"invoice_key" : 401,
		"customer_key" : 46,
		"track_key" : 2721,
		"invoice_date_key" : 20131104,
		"billing_address" : "3 Chatham Street",
		"billing_city" : "Dublin",
		"billing_state" : "Dublin",
		"billing_country" : "Ireland",
		"billing_postal_code" : null,
		"unit_price" : 0.99,
		"quantity" : 1,
		"invoice_total" : 3.96
	},
	{
		"fact_invoice_key" : 2170,
		"invoice_key" : 401,
		"customer_key" : 46,
		"track_key" : 2723,
		"invoice_date_key" : 20131104,
		"billing_address" : "3 Chatham Street",
		"billing_city" : "Dublin",
		"billing_state" : "Dublin",
		"billing_country" : "Ireland",
		"billing_postal_code" : null,
		"unit_price" : 0.99,
		"quantity" : 1,
		"invoice_total" : 3.96
	},
	{
		"fact_invoice_key" : 2171,
		"invoice_key" : 401,
		"customer_key" : 46,
		"track_key" : 2725,
		"invoice_date_key" : 20131104,
		"billing_address" : "3 Chatham Street",
		"billing_city" : "Dublin",
		"billing_state" : "Dublin",
		"billing_country" : "Ireland",
		"billing_postal_code" : null,
		"unit_price" : 0.99,
		"quantity" : 1,
		"invoice_total" : 3.96
	},
	{
		"fact_invoice_key" : 2172,
		"invoice_key" : 401,
		"customer_key" : 46,
		"track_key" : 2727,
		"invoice_date_key" : 20131104,
		"billing_address" : "3 Chatham Street",
		"billing_city" : "Dublin",
		"billing_state" : "Dublin",
		"billing_country" : "Ireland",
		"billing_postal_code" : null,
		"unit_price" : 0.99,
		"quantity" : 1,
		"invoice_total" : 3.96
	},
	{
		"fact_invoice_key" : 2173,
		"invoice_key" : 402,
		"customer_key" : 50,
		"track_key" : 2731,
		"invoice_date_key" : 20131105,
		"billing_address" : "C/ San Bernardo 85",
		"billing_city" : "Madrid",
		"billing_state" : null,
		"billing_country" : "Spain",
		"billing_postal_code" : "28015",
		"unit_price" : 0.99,
		"quantity" : 1,
		"invoice_total" : 5.94
	},
	{
		"fact_invoice_key" : 2174,
		"invoice_key" : 402,
		"customer_key" : 50,
		"track_key" : 2735,
		"invoice_date_key" : 20131105,
		"billing_address" : "C/ San Bernardo 85",
		"billing_city" : "Madrid",
		"billing_state" : null,
		"billing_country" : "Spain",
		"billing_postal_code" : "28015",
		"unit_price" : 0.99,
		"quantity" : 1,
		"invoice_total" : 5.94
	},
	{
		"fact_invoice_key" : 2175,
		"invoice_key" : 402,
		"customer_key" : 50,
		"track_key" : 2739,
		"invoice_date_key" : 20131105,
		"billing_address" : "C/ San Bernardo 85",
		"billing_city" : "Madrid",
		"billing_state" : null,
		"billing_country" : "Spain",
		"billing_postal_code" : "28015",
		"unit_price" : 0.99,
		"quantity" : 1,
		"invoice_total" : 5.94
	},
	{
		"fact_invoice_key" : 2176,
		"invoice_key" : 402,
		"customer_key" : 50,
		"track_key" : 2743,
		"invoice_date_key" : 20131105,
		"billing_address" : "C/ San Bernardo 85",
		"billing_city" : "Madrid",
		"billing_state" : null,
		"billing_country" : "Spain",
		"billing_postal_code" : "28015",
		"unit_price" : 0.99,
		"quantity" : 1,
		"invoice_total" : 5.94
	},
	{
		"fact_invoice_key" : 2177,
		"invoice_key" : 402,
		"customer_key" : 50,
		"track_key" : 2747,
		"invoice_date_key" : 20131105,
		"billing_address" : "C/ San Bernardo 85",
		"billing_city" : "Madrid",
		"billing_state" : null,
		"billing_country" : "Spain",
		"billing_postal_code" : "28015",
		"unit_price" : 0.99,
		"quantity" : 1,
		"invoice_total" : 5.94
	},
	{
		"fact_invoice_key" : 2178,
		"invoice_key" : 402,
		"customer_key" : 50,
		"track_key" : 2751,
		"invoice_date_key" : 20131105,
		"billing_address" : "C/ San Bernardo 85",
		"billing_city" : "Madrid",
		"billing_state" : null,
		"billing_country" : "Spain",
		"billing_postal_code" : "28015",
		"unit_price" : 0.99,
		"quantity" : 1,
		"invoice_total" : 5.94
	},
	{
		"fact_invoice_key" : 2179,
		"invoice_key" : 403,
		"customer_key" : 56,
		"track_key" : 2757,
		"invoice_date_key" : 20131108,
		"billing_address" : "307 Macacha Güemes",
		"billing_city" : "Buenos Aires",
		"billing_state" : null,
		"billing_country" : "Argentina",
		"billing_postal_code" : "1106",
		"unit_price" : 0.99,
		"quantity" : 1,
		"invoice_total" : 8.91
	},
	{
		"fact_invoice_key" : 2180,
		"invoice_key" : 403,
		"customer_key" : 56,
		"track_key" : 2763,
		"invoice_date_key" : 20131108,
		"billing_address" : "307 Macacha Güemes",
		"billing_city" : "Buenos Aires",
		"billing_state" : null,
		"billing_country" : "Argentina",
		"billing_postal_code" : "1106",
		"unit_price" : 0.99,
		"quantity" : 1,
		"invoice_total" : 8.91
	},
	{
		"fact_invoice_key" : 2181,
		"invoice_key" : 403,
		"customer_key" : 56,
		"track_key" : 2769,
		"invoice_date_key" : 20131108,
		"billing_address" : "307 Macacha Güemes",
		"billing_city" : "Buenos Aires",
		"billing_state" : null,
		"billing_country" : "Argentina",
		"billing_postal_code" : "1106",
		"unit_price" : 0.99,
		"quantity" : 1,
		"invoice_total" : 8.91
	},
	{
		"fact_invoice_key" : 2182,
		"invoice_key" : 403,
		"customer_key" : 56,
		"track_key" : 2775,
		"invoice_date_key" : 20131108,
		"billing_address" : "307 Macacha Güemes",
		"billing_city" : "Buenos Aires",
		"billing_state" : null,
		"billing_country" : "Argentina",
		"billing_postal_code" : "1106",
		"unit_price" : 0.99,
		"quantity" : 1,
		"invoice_total" : 8.91
	},
	{
		"fact_invoice_key" : 2183,
		"invoice_key" : 403,
		"customer_key" : 56,
		"track_key" : 2781,
		"invoice_date_key" : 20131108,
		"billing_address" : "307 Macacha Güemes",
		"billing_city" : "Buenos Aires",
		"billing_state" : null,
		"billing_country" : "Argentina",
		"billing_postal_code" : "1106",
		"unit_price" : 0.99,
		"quantity" : 1,
		"invoice_total" : 8.91
	},
	{
		"fact_invoice_key" : 2184,
		"invoice_key" : 403,
		"customer_key" : 56,
		"track_key" : 2787,
		"invoice_date_key" : 20131108,
		"billing_address" : "307 Macacha Güemes",
		"billing_city" : "Buenos Aires",
		"billing_state" : null,
		"billing_country" : "Argentina",
		"billing_postal_code" : "1106",
		"unit_price" : 0.99,
		"quantity" : 1,
		"invoice_total" : 8.91
	},
	{
		"fact_invoice_key" : 2185,
		"invoice_key" : 403,
		"customer_key" : 56,
		"track_key" : 2793,
		"invoice_date_key" : 20131108,
		"billing_address" : "307 Macacha Güemes",
		"billing_city" : "Buenos Aires",
		"billing_state" : null,
		"billing_country" : "Argentina",
		"billing_postal_code" : "1106",
		"unit_price" : 0.99,
		"quantity" : 1,
		"invoice_total" : 8.91
	},
	{
		"fact_invoice_key" : 2186,
		"invoice_key" : 403,
		"customer_key" : 56,
		"track_key" : 2799,
		"invoice_date_key" : 20131108,
		"billing_address" : "307 Macacha Güemes",
		"billing_city" : "Buenos Aires",
		"billing_state" : null,
		"billing_country" : "Argentina",
		"billing_postal_code" : "1106",
		"unit_price" : 0.99,
		"quantity" : 1,
		"invoice_total" : 8.91
	},
	{
		"fact_invoice_key" : 2187,
		"invoice_key" : 403,
		"customer_key" : 56,
		"track_key" : 2805,
		"invoice_date_key" : 20131108,
		"billing_address" : "307 Macacha Güemes",
		"billing_city" : "Buenos Aires",
		"billing_state" : null,
		"billing_country" : "Argentina",
		"billing_postal_code" : "1106",
		"unit_price" : 0.99,
		"quantity" : 1,
		"invoice_total" : 8.91
	},
	{
		"fact_invoice_key" : 2188,
		"invoice_key" : 404,
		"customer_key" : 6,
		"track_key" : 2814,
		"invoice_date_key" : 20131113,
		"billing_address" : "Rilská 3174/6",
		"billing_city" : "Prague",
		"billing_state" : null,
		"billing_country" : "Czech Republic",
		"billing_postal_code" : "14300",
		"unit_price" : 0.99,
		"quantity" : 1,
		"invoice_total" : 25.86
	},
	{
		"fact_invoice_key" : 2189,
		"invoice_key" : 404,
		"customer_key" : 6,
		"track_key" : 2823,
		"invoice_date_key" : 20131113,
		"billing_address" : "Rilská 3174/6",
		"billing_city" : "Prague",
		"billing_state" : null,
		"billing_country" : "Czech Republic",
		"billing_postal_code" : "14300",
		"unit_price" : 1.99,
		"quantity" : 1,
		"invoice_total" : 25.86
	},
	{
		"fact_invoice_key" : 2190,
		"invoice_key" : 404,
		"customer_key" : 6,
		"track_key" : 2832,
		"invoice_date_key" : 20131113,
		"billing_address" : "Rilská 3174/6",
		"billing_city" : "Prague",
		"billing_state" : null,
		"billing_country" : "Czech Republic",
		"billing_postal_code" : "14300",
		"unit_price" : 1.99,
		"quantity" : 1,
		"invoice_total" : 25.86
	},
	{
		"fact_invoice_key" : 2191,
		"invoice_key" : 404,
		"customer_key" : 6,
		"track_key" : 2841,
		"invoice_date_key" : 20131113,
		"billing_address" : "Rilská 3174/6",
		"billing_city" : "Prague",
		"billing_state" : null,
		"billing_country" : "Czech Republic",
		"billing_postal_code" : "14300",
		"unit_price" : 1.99,
		"quantity" : 1,
		"invoice_total" : 25.86
	},
	{
		"fact_invoice_key" : 2192,
		"invoice_key" : 404,
		"customer_key" : 6,
		"track_key" : 2850,
		"invoice_date_key" : 20131113,
		"billing_address" : "Rilská 3174/6",
		"billing_city" : "Prague",
		"billing_state" : null,
		"billing_country" : "Czech Republic",
		"billing_postal_code" : "14300",
		"unit_price" : 1.99,
		"quantity" : 1,
		"invoice_total" : 25.86
	},
	{
		"fact_invoice_key" : 2193,
		"invoice_key" : 404,
		"customer_key" : 6,
		"track_key" : 2859,
		"invoice_date_key" : 20131113,
		"billing_address" : "Rilská 3174/6",
		"billing_city" : "Prague",
		"billing_state" : null,
		"billing_country" : "Czech Republic",
		"billing_postal_code" : "14300",
		"unit_price" : 1.99,
		"quantity" : 1,
		"invoice_total" : 25.86
	},
	{
		"fact_invoice_key" : 2194,
		"invoice_key" : 404,
		"customer_key" : 6,
		"track_key" : 2868,
		"invoice_date_key" : 20131113,
		"billing_address" : "Rilská 3174/6",
		"billing_city" : "Prague",
		"billing_state" : null,
		"billing_country" : "Czech Republic",
		"billing_postal_code" : "14300",
		"unit_price" : 1.99,
		"quantity" : 1,
		"invoice_total" : 25.86
	},
	{
		"fact_invoice_key" : 2195,
		"invoice_key" : 404,
		"customer_key" : 6,
		"track_key" : 2877,
		"invoice_date_key" : 20131113,
		"billing_address" : "Rilská 3174/6",
		"billing_city" : "Prague",
		"billing_state" : null,
		"billing_country" : "Czech Republic",
		"billing_postal_code" : "14300",
		"unit_price" : 1.99,
		"quantity" : 1,
		"invoice_total" : 25.86
	},
	{
		"fact_invoice_key" : 2196,
		"invoice_key" : 404,
		"customer_key" : 6,
		"track_key" : 2886,
		"invoice_date_key" : 20131113,
		"billing_address" : "Rilská 3174/6",
		"billing_city" : "Prague",
		"billing_state" : null,
		"billing_country" : "Czech Republic",
		"billing_postal_code" : "14300",
		"unit_price" : 1.99,
		"quantity" : 1,
		"invoice_total" : 25.86
	},
	{
		"fact_invoice_key" : 2197,
		"invoice_key" : 404,
		"customer_key" : 6,
		"track_key" : 2895,
		"invoice_date_key" : 20131113,
		"billing_address" : "Rilská 3174/6",
		"billing_city" : "Prague",
		"billing_state" : null,
		"billing_country" : "Czech Republic",
		"billing_postal_code" : "14300",
		"unit_price" : 1.99,
		"quantity" : 1,
		"invoice_total" : 25.86
	},
	{
		"fact_invoice_key" : 2198,
		"invoice_key" : 404,
		"customer_key" : 6,
		"track_key" : 2904,
		"invoice_date_key" : 20131113,
		"billing_address" : "Rilská 3174/6",
		"billing_city" : "Prague",
		"billing_state" : null,
		"billing_country" : "Czech Republic",
		"billing_postal_code" : "14300",
		"unit_price" : 1.99,
		"quantity" : 1,
		"invoice_total" : 25.86
	},
	{
		"fact_invoice_key" : 2199,
		"invoice_key" : 404,
		"customer_key" : 6,
		"track_key" : 2913,
		"invoice_date_key" : 20131113,
		"billing_address" : "Rilská 3174/6",
		"billing_city" : "Prague",
		"billing_state" : null,
		"billing_country" : "Czech Republic",
		"billing_postal_code" : "14300",
		"unit_price" : 1.99,
		"quantity" : 1,
		"invoice_total" : 25.86
	},
	{
		"fact_invoice_key" : 2200,
		"invoice_key" : 404,
		"customer_key" : 6,
		"track_key" : 2922,
		"invoice_date_key" : 20131113,
		"billing_address" : "Rilská 3174/6",
		"billing_city" : "Prague",
		"billing_state" : null,
		"billing_country" : "Czech Republic",
		"billing_postal_code" : "14300",
		"unit_price" : 1.99,
		"quantity" : 1,
		"invoice_total" : 25.86
	},
	{
		"fact_invoice_key" : 2201,
		"invoice_key" : 404,
		"customer_key" : 6,
		"track_key" : 2931,
		"invoice_date_key" : 20131113,
		"billing_address" : "Rilská 3174/6",
		"billing_city" : "Prague",
		"billing_state" : null,
		"billing_country" : "Czech Republic",
		"billing_postal_code" : "14300",
		"unit_price" : 0.99,
		"quantity" : 1,
		"invoice_total" : 25.86
	},
	{
		"fact_invoice_key" : 2202,
		"invoice_key" : 405,
		"customer_key" : 20,
		"track_key" : 2945,
		"invoice_date_key" : 20131121,
		"billing_address" : "541 Del Medio Avenue",
		"billing_city" : "Mountain View",
		"billing_state" : "CA",
		"billing_country" : "USA",
		"billing_postal_code" : "94040-111",
		"unit_price" : 0.99,
		"quantity" : 1,
		"invoice_total" : 0.99
	},
	{
		"fact_invoice_key" : 2203,
		"invoice_key" : 406,
		"customer_key" : 21,
		"track_key" : 2946,
		"invoice_date_key" : 20131204,
		"billing_address" : "801 W 4th Street",
		"billing_city" : "Reno",
		"billing_state" : "NV",
		"billing_country" : "USA",
		"billing_postal_code" : "89503",
		"unit_price" : 0.99,
		"quantity" : 1,
		"invoice_total" : 1.98
	},
	{
		"fact_invoice_key" : 2204,
		"invoice_key" : 406,
		"customer_key" : 21,
		"track_key" : 2947,
		"invoice_date_key" : 20131204,
		"billing_address" : "801 W 4th Street",
		"billing_city" : "Reno",
		"billing_state" : "NV",
		"billing_country" : "USA",
		"billing_postal_code" : "89503",
		"unit_price" : 0.99,
		"quantity" : 1,
		"invoice_total" : 1.98
	},
	{
		"fact_invoice_key" : 2205,
		"invoice_key" : 407,
		"customer_key" : 23,
		"track_key" : 2949,
		"invoice_date_key" : 20131204,
		"billing_address" : "69 Salem Street",
		"billing_city" : "Boston",
		"billing_state" : "MA",
		"billing_country" : "USA",
		"billing_postal_code" : "2113",
		"unit_price" : 0.99,
		"quantity" : 1,
		"invoice_total" : 1.98
	},
	{
		"fact_invoice_key" : 2206,
		"invoice_key" : 407,
		"customer_key" : 23,
		"track_key" : 2951,
		"invoice_date_key" : 20131204,
		"billing_address" : "69 Salem Street",
		"billing_city" : "Boston",
		"billing_state" : "MA",
		"billing_country" : "USA",
		"billing_postal_code" : "2113",
		"unit_price" : 0.99,
		"quantity" : 1,
		"invoice_total" : 1.98
	},
	{
		"fact_invoice_key" : 2207,
		"invoice_key" : 408,
		"customer_key" : 25,
		"track_key" : 2953,
		"invoice_date_key" : 20131205,
		"billing_address" : "319 N. Frances Street",
		"billing_city" : "Madison",
		"billing_state" : "WI",
		"billing_country" : "USA",
		"billing_postal_code" : "53703",
		"unit_price" : 0.99,
		"quantity" : 1,
		"invoice_total" : 3.96
	},
	{
		"fact_invoice_key" : 2208,
		"invoice_key" : 408,
		"customer_key" : 25,
		"track_key" : 2955,
		"invoice_date_key" : 20131205,
		"billing_address" : "319 N. Frances Street",
		"billing_city" : "Madison",
		"billing_state" : "WI",
		"billing_country" : "USA",
		"billing_postal_code" : "53703",
		"unit_price" : 0.99,
		"quantity" : 1,
		"invoice_total" : 3.96
	},
	{
		"fact_invoice_key" : 2209,
		"invoice_key" : 408,
		"customer_key" : 25,
		"track_key" : 2957,
		"invoice_date_key" : 20131205,
		"billing_address" : "319 N. Frances Street",
		"billing_city" : "Madison",
		"billing_state" : "WI",
		"billing_country" : "USA",
		"billing_postal_code" : "53703",
		"unit_price" : 0.99,
		"quantity" : 1,
		"invoice_total" : 3.96
	},
	{
		"fact_invoice_key" : 2210,
		"invoice_key" : 408,
		"customer_key" : 25,
		"track_key" : 2959,
		"invoice_date_key" : 20131205,
		"billing_address" : "319 N. Frances Street",
		"billing_city" : "Madison",
		"billing_state" : "WI",
		"billing_country" : "USA",
		"billing_postal_code" : "53703",
		"unit_price" : 0.99,
		"quantity" : 1,
		"invoice_total" : 3.96
	},
	{
		"fact_invoice_key" : 2211,
		"invoice_key" : 409,
		"customer_key" : 29,
		"track_key" : 2963,
		"invoice_date_key" : 20131206,
		"billing_address" : "796 Dundas Street West",
		"billing_city" : "Toronto",
		"billing_state" : "ON",
		"billing_country" : "Canada",
		"billing_postal_code" : "M6J 1V1",
		"unit_price" : 0.99,
		"quantity" : 1,
		"invoice_total" : 5.94
	},
	{
		"fact_invoice_key" : 2212,
		"invoice_key" : 409,
		"customer_key" : 29,
		"track_key" : 2967,
		"invoice_date_key" : 20131206,
		"billing_address" : "796 Dundas Street West",
		"billing_city" : "Toronto",
		"billing_state" : "ON",
		"billing_country" : "Canada",
		"billing_postal_code" : "M6J 1V1",
		"unit_price" : 0.99,
		"quantity" : 1,
		"invoice_total" : 5.94
	},
	{
		"fact_invoice_key" : 2213,
		"invoice_key" : 409,
		"customer_key" : 29,
		"track_key" : 2971,
		"invoice_date_key" : 20131206,
		"billing_address" : "796 Dundas Street West",
		"billing_city" : "Toronto",
		"billing_state" : "ON",
		"billing_country" : "Canada",
		"billing_postal_code" : "M6J 1V1",
		"unit_price" : 0.99,
		"quantity" : 1,
		"invoice_total" : 5.94
	},
	{
		"fact_invoice_key" : 2214,
		"invoice_key" : 409,
		"customer_key" : 29,
		"track_key" : 2975,
		"invoice_date_key" : 20131206,
		"billing_address" : "796 Dundas Street West",
		"billing_city" : "Toronto",
		"billing_state" : "ON",
		"billing_country" : "Canada",
		"billing_postal_code" : "M6J 1V1",
		"unit_price" : 0.99,
		"quantity" : 1,
		"invoice_total" : 5.94
	},
	{
		"fact_invoice_key" : 2215,
		"invoice_key" : 409,
		"customer_key" : 29,
		"track_key" : 2979,
		"invoice_date_key" : 20131206,
		"billing_address" : "796 Dundas Street West",
		"billing_city" : "Toronto",
		"billing_state" : "ON",
		"billing_country" : "Canada",
		"billing_postal_code" : "M6J 1V1",
		"unit_price" : 0.99,
		"quantity" : 1,
		"invoice_total" : 5.94
	},
	{
		"fact_invoice_key" : 2216,
		"invoice_key" : 409,
		"customer_key" : 29,
		"track_key" : 2983,
		"invoice_date_key" : 20131206,
		"billing_address" : "796 Dundas Street West",
		"billing_city" : "Toronto",
		"billing_state" : "ON",
		"billing_country" : "Canada",
		"billing_postal_code" : "M6J 1V1",
		"unit_price" : 0.99,
		"quantity" : 1,
		"invoice_total" : 5.94
	},
	{
		"fact_invoice_key" : 2217,
		"invoice_key" : 410,
		"customer_key" : 35,
		"track_key" : 2989,
		"invoice_date_key" : 20131209,
		"billing_address" : "Rua dos Campeões Europeus de Viena, 4350",
		"billing_city" : "Porto",
		"billing_state" : null,
		"billing_country" : "Portugal",
		"billing_postal_code" : null,
		"unit_price" : 0.99,
		"quantity" : 1,
		"invoice_total" : 8.91
	},
	{
		"fact_invoice_key" : 2218,
		"invoice_key" : 410,
		"customer_key" : 35,
		"track_key" : 2995,
		"invoice_date_key" : 20131209,
		"billing_address" : "Rua dos Campeões Europeus de Viena, 4350",
		"billing_city" : "Porto",
		"billing_state" : null,
		"billing_country" : "Portugal",
		"billing_postal_code" : null,
		"unit_price" : 0.99,
		"quantity" : 1,
		"invoice_total" : 8.91
	},
	{
		"fact_invoice_key" : 2219,
		"invoice_key" : 410,
		"customer_key" : 35,
		"track_key" : 3001,
		"invoice_date_key" : 20131209,
		"billing_address" : "Rua dos Campeões Europeus de Viena, 4350",
		"billing_city" : "Porto",
		"billing_state" : null,
		"billing_country" : "Portugal",
		"billing_postal_code" : null,
		"unit_price" : 0.99,
		"quantity" : 1,
		"invoice_total" : 8.91
	},
	{
		"fact_invoice_key" : 2220,
		"invoice_key" : 410,
		"customer_key" : 35,
		"track_key" : 3007,
		"invoice_date_key" : 20131209,
		"billing_address" : "Rua dos Campeões Europeus de Viena, 4350",
		"billing_city" : "Porto",
		"billing_state" : null,
		"billing_country" : "Portugal",
		"billing_postal_code" : null,
		"unit_price" : 0.99,
		"quantity" : 1,
		"invoice_total" : 8.91
	},
	{
		"fact_invoice_key" : 2221,
		"invoice_key" : 410,
		"customer_key" : 35,
		"track_key" : 3013,
		"invoice_date_key" : 20131209,
		"billing_address" : "Rua dos Campeões Europeus de Viena, 4350",
		"billing_city" : "Porto",
		"billing_state" : null,
		"billing_country" : "Portugal",
		"billing_postal_code" : null,
		"unit_price" : 0.99,
		"quantity" : 1,
		"invoice_total" : 8.91
	},
	{
		"fact_invoice_key" : 2222,
		"invoice_key" : 410,
		"customer_key" : 35,
		"track_key" : 3019,
		"invoice_date_key" : 20131209,
		"billing_address" : "Rua dos Campeões Europeus de Viena, 4350",
		"billing_city" : "Porto",
		"billing_state" : null,
		"billing_country" : "Portugal",
		"billing_postal_code" : null,
		"unit_price" : 0.99,
		"quantity" : 1,
		"invoice_total" : 8.91
	},
	{
		"fact_invoice_key" : 2223,
		"invoice_key" : 410,
		"customer_key" : 35,
		"track_key" : 3025,
		"invoice_date_key" : 20131209,
		"billing_address" : "Rua dos Campeões Europeus de Viena, 4350",
		"billing_city" : "Porto",
		"billing_state" : null,
		"billing_country" : "Portugal",
		"billing_postal_code" : null,
		"unit_price" : 0.99,
		"quantity" : 1,
		"invoice_total" : 8.91
	},
	{
		"fact_invoice_key" : 2224,
		"invoice_key" : 410,
		"customer_key" : 35,
		"track_key" : 3031,
		"invoice_date_key" : 20131209,
		"billing_address" : "Rua dos Campeões Europeus de Viena, 4350",
		"billing_city" : "Porto",
		"billing_state" : null,
		"billing_country" : "Portugal",
		"billing_postal_code" : null,
		"unit_price" : 0.99,
		"quantity" : 1,
		"invoice_total" : 8.91
	},
	{
		"fact_invoice_key" : 2225,
		"invoice_key" : 410,
		"customer_key" : 35,
		"track_key" : 3037,
		"invoice_date_key" : 20131209,
		"billing_address" : "Rua dos Campeões Europeus de Viena, 4350",
		"billing_city" : "Porto",
		"billing_state" : null,
		"billing_country" : "Portugal",
		"billing_postal_code" : null,
		"unit_price" : 0.99,
		"quantity" : 1,
		"invoice_total" : 8.91
	},
	{
		"fact_invoice_key" : 2226,
		"invoice_key" : 411,
		"customer_key" : 44,
		"track_key" : 3046,
		"invoice_date_key" : 20131214,
		"billing_address" : "Porthaninkatu 9",
		"billing_city" : "Helsinki",
		"billing_state" : null,
		"billing_country" : "Finland",
		"billing_postal_code" : "00530",
		"unit_price" : 0.99,
		"quantity" : 1,
		"invoice_total" : 13.86
	},
	{
		"fact_invoice_key" : 2227,
		"invoice_key" : 411,
		"customer_key" : 44,
		"track_key" : 3055,
		"invoice_date_key" : 20131214,
		"billing_address" : "Porthaninkatu 9",
		"billing_city" : "Helsinki",
		"billing_state" : null,
		"billing_country" : "Finland",
		"billing_postal_code" : "00530",
		"unit_price" : 0.99,
		"quantity" : 1,
		"invoice_total" : 13.86
	},
	{
		"fact_invoice_key" : 2228,
		"invoice_key" : 411,
		"customer_key" : 44,
		"track_key" : 3064,
		"invoice_date_key" : 20131214,
		"billing_address" : "Porthaninkatu 9",
		"billing_city" : "Helsinki",
		"billing_state" : null,
		"billing_country" : "Finland",
		"billing_postal_code" : "00530",
		"unit_price" : 0.99,
		"quantity" : 1,
		"invoice_total" : 13.86
	},
	{
		"fact_invoice_key" : 2229,
		"invoice_key" : 411,
		"customer_key" : 44,
		"track_key" : 3073,
		"invoice_date_key" : 20131214,
		"billing_address" : "Porthaninkatu 9",
		"billing_city" : "Helsinki",
		"billing_state" : null,
		"billing_country" : "Finland",
		"billing_postal_code" : "00530",
		"unit_price" : 0.99,
		"quantity" : 1,
		"invoice_total" : 13.86
	},
	{
		"fact_invoice_key" : 2230,
		"invoice_key" : 411,
		"customer_key" : 44,
		"track_key" : 3082,
		"invoice_date_key" : 20131214,
		"billing_address" : "Porthaninkatu 9",
		"billing_city" : "Helsinki",
		"billing_state" : null,
		"billing_country" : "Finland",
		"billing_postal_code" : "00530",
		"unit_price" : 0.99,
		"quantity" : 1,
		"invoice_total" : 13.86
	},
	{
		"fact_invoice_key" : 2231,
		"invoice_key" : 411,
		"customer_key" : 44,
		"track_key" : 3091,
		"invoice_date_key" : 20131214,
		"billing_address" : "Porthaninkatu 9",
		"billing_city" : "Helsinki",
		"billing_state" : null,
		"billing_country" : "Finland",
		"billing_postal_code" : "00530",
		"unit_price" : 0.99,
		"quantity" : 1,
		"invoice_total" : 13.86
	},
	{
		"fact_invoice_key" : 2232,
		"invoice_key" : 411,
		"customer_key" : 44,
		"track_key" : 3100,
		"invoice_date_key" : 20131214,
		"billing_address" : "Porthaninkatu 9",
		"billing_city" : "Helsinki",
		"billing_state" : null,
		"billing_country" : "Finland",
		"billing_postal_code" : "00530",
		"unit_price" : 0.99,
		"quantity" : 1,
		"invoice_total" : 13.86
	},
	{
		"fact_invoice_key" : 2233,
		"invoice_key" : 411,
		"customer_key" : 44,
		"track_key" : 3109,
		"invoice_date_key" : 20131214,
		"billing_address" : "Porthaninkatu 9",
		"billing_city" : "Helsinki",
		"billing_state" : null,
		"billing_country" : "Finland",
		"billing_postal_code" : "00530",
		"unit_price" : 0.99,
		"quantity" : 1,
		"invoice_total" : 13.86
	},
	{
		"fact_invoice_key" : 2234,
		"invoice_key" : 411,
		"customer_key" : 44,
		"track_key" : 3118,
		"invoice_date_key" : 20131214,
		"billing_address" : "Porthaninkatu 9",
		"billing_city" : "Helsinki",
		"billing_state" : null,
		"billing_country" : "Finland",
		"billing_postal_code" : "00530",
		"unit_price" : 0.99,
		"quantity" : 1,
		"invoice_total" : 13.86
	},
	{
		"fact_invoice_key" : 2235,
		"invoice_key" : 411,
		"customer_key" : 44,
		"track_key" : 3127,
		"invoice_date_key" : 20131214,
		"billing_address" : "Porthaninkatu 9",
		"billing_city" : "Helsinki",
		"billing_state" : null,
		"billing_country" : "Finland",
		"billing_postal_code" : "00530",
		"unit_price" : 0.99,
		"quantity" : 1,
		"invoice_total" : 13.86
	},
	{
		"fact_invoice_key" : 2236,
		"invoice_key" : 411,
		"customer_key" : 44,
		"track_key" : 3136,
		"invoice_date_key" : 20131214,
		"billing_address" : "Porthaninkatu 9",
		"billing_city" : "Helsinki",
		"billing_state" : null,
		"billing_country" : "Finland",
		"billing_postal_code" : "00530",
		"unit_price" : 0.99,
		"quantity" : 1,
		"invoice_total" : 13.86
	},
	{
		"fact_invoice_key" : 2237,
		"invoice_key" : 411,
		"customer_key" : 44,
		"track_key" : 3145,
		"invoice_date_key" : 20131214,
		"billing_address" : "Porthaninkatu 9",
		"billing_city" : "Helsinki",
		"billing_state" : null,
		"billing_country" : "Finland",
		"billing_postal_code" : "00530",
		"unit_price" : 0.99,
		"quantity" : 1,
		"invoice_total" : 13.86
	},
	{
		"fact_invoice_key" : 2238,
		"invoice_key" : 411,
		"customer_key" : 44,
		"track_key" : 3154,
		"invoice_date_key" : 20131214,
		"billing_address" : "Porthaninkatu 9",
		"billing_city" : "Helsinki",
		"billing_state" : null,
		"billing_country" : "Finland",
		"billing_postal_code" : "00530",
		"unit_price" : 0.99,
		"quantity" : 1,
		"invoice_total" : 13.86
	},
	{
		"fact_invoice_key" : 2239,
		"invoice_key" : 411,
		"customer_key" : 44,
		"track_key" : 3163,
		"invoice_date_key" : 20131214,
		"billing_address" : "Porthaninkatu 9",
		"billing_city" : "Helsinki",
		"billing_state" : null,
		"billing_country" : "Finland",
		"billing_postal_code" : "00530",
		"unit_price" : 0.99,
		"quantity" : 1,
		"invoice_total" : 13.86
	},
	{
		"fact_invoice_key" : 2240,
		"invoice_key" : 412,
		"customer_key" : 58,
		"track_key" : 3177,
		"invoice_date_key" : 20131222,
		"billing_address" : "12,Community Centre",
		"billing_city" : "Delhi",
		"billing_state" : null,
		"billing_country" : "India",
		"billing_postal_code" : "110017",
		"unit_price" : 1.99,
		"quantity" : 1,
		"invoice_total" : 1.99
	}
]
